[
  {
    "station_no": "2",
    "building": "3",
    "village": "",
    "lat": 12.988452,
    "lng": 80.18237599999999,
    "found": true
  },
  {
    "station_no": "2",
    "building": "Panchayat Union Primary School, South Side Building North Facing Iyyappanthangal-600056.",
    "village": "South Side Building North Facing Iyyappanthangal",
    "lat": 13.0506077,
    "lng": 80.0988127,
    "found": true
  },
  {
    "station_no": "3",
    "building": "Panchayat Union Primary School, East Facing West Building, Iyyappanthangal- 600056.",
    "village": "East Facing West Building",
    "lat": 13.0506077,
    "lng": 80.0988127,
    "found": true
  },
  {
    "station_no": "4",
    "building": "Panchayat Union Primary School, North Facing, Left Corner New Building Room No 1, Iyyappanthangal-500056.",
    "village": "North Facing",
    "lat": 13.0541089,
    "lng": 80.1543169,
    "found": true
  },
  {
    "station_no": "5",
    "building": "Panchayat union primary school, East Facing west building , Iyyappanthangal- 600056.",
    "village": "East Facing west building",
    "lat": 13.0506077,
    "lng": 80.0988127,
    "found": true
  },
  {
    "station_no": "6",
    "building": "Panchayat union primary school, North Facing Left Corner New Building Room No 02, Iyyappanthangal-600056.",
    "village": "North Facing Left Corner New Building Room No",
    "lat": 13.0484624,
    "lng": 80.1348127,
    "found": true
  },
  {
    "station_no": "7",
    "building": "Panchayat union primary school west building, Iyyappanthangal -600056.",
    "village": "Iyyappanthangal",
    "lat": 13.0237241,
    "lng": 80.1225821,
    "found": true
  },
  {
    "station_no": "8",
    "building": "Government Higher Secondary School Iyyappanthangal, Iyyappanthangal 600056.",
    "village": "Iyyappanthangal",
    "lat": 12.8227048,
    "lng": 79.6965056,
    "found": true
  },
  {
    "station_no": "9",
    "building": "Government Higher Secondary School Iyyappanthangal, Iyyappanthangal 600056.",
    "village": "Iyyappanthangal",
    "lat": 12.8227048,
    "lng": 79.6965056,
    "found": true
  },
  {
    "station_no": "10",
    "building": "Government Higher Secondary School Iyyappanthangal, Iyyappanthangal 600056.",
    "village": "Iyyappanthangal",
    "lat": 12.8227048,
    "lng": 79.6965056,
    "found": true
  },
  {
    "station_no": "11",
    "building": "Government Higher Secondary School Iyyappanthangal, Iyyappanthangal 600056.",
    "village": "Iyyappanthangal",
    "lat": 12.8227048,
    "lng": 79.6965056,
    "found": true
  },
  {
    "station_no": "12",
    "building": "Government Higher Secondary School Iyyappanthangal, Iyyappanthangal 600056.",
    "village": "Iyyappanthangal",
    "lat": 12.8227048,
    "lng": 79.6965056,
    "found": true
  },
  {
    "station_no": "13",
    "building": "Government Higher Secondary School Iyyappanthangal, Iyyappanthangal 600056.",
    "village": "Iyyappanthangal",
    "lat": 12.8227048,
    "lng": 79.6965056,
    "found": true
  },
  {
    "station_no": "14",
    "building": "Government Higher Secondary School, North Facing, Class No. 8, Iyyappanthangal - 600056",
    "village": "North Facing",
    "lat": 13.0374408,
    "lng": 80.13546339999999,
    "found": true
  },
  {
    "station_no": "15",
    "building": "Kalakshetra Higher Secondary School Sousth Facing Mount Poonamalli High Road Iyyappanthangal 600056",
    "village": "",
    "lat": 13.0413894,
    "lng": 80.1267136,
    "found": true
  },
  {
    "station_no": "16",
    "building": "Kalakshetra Higher Secondary School Sousth Facing Mount Poonamalli High Road Iyyappanthangal 600056",
    "village": "",
    "lat": 13.0413894,
    "lng": 80.1267136,
    "found": true
  },
  {
    "station_no": "17",
    "building": "Government Higher Secondary School, North Facing Building, Iyyappanthangal - 600056",
    "village": "North Facing Building",
    "lat": 13.0212213,
    "lng": 80.1669572,
    "found": true
  },
  {
    "station_no": "18",
    "building": "Panchayat union primary school, North Facing Building Room No. 1 , Iyyappanthangal - 600056",
    "village": "North Facing Building Room No",
    "lat": 13.0397178,
    "lng": 80.1336488,
    "found": true
  },
  {
    "station_no": "19",
    "building": "Panchayat union primary school, North Facing Building Room No. 2, Iyyappanthangal - 600056",
    "village": "North Facing Building Room No",
    "lat": 13.0397178,
    "lng": 80.1336488,
    "found": true
  },
  {
    "station_no": "20",
    "building": "Panchayat union primary school, North Facing Building Room No. 3, Iyyappanthangal - 600056",
    "village": "North Facing Building Room No",
    "lat": 13.0397178,
    "lng": 80.1336488,
    "found": true
  },
  {
    "station_no": "21",
    "building": "Panchayat union primary school, North Facing Building Room No. 4, Iyyappanthangal - 600056",
    "village": "North Facing Building Room No",
    "lat": 13.0397178,
    "lng": 80.1336488,
    "found": true
  },
  {
    "station_no": "22",
    "building": "Kundrathur Panchayat Union Primary School Iyyappanthangal, Iyyappanthangal 600056.",
    "village": "Iyyappanthangal",
    "lat": 13.0330749,
    "lng": 80.1405467,
    "found": true
  },
  {
    "station_no": "23",
    "building": "Kundrathur Panchayat Union Primary School Iyyappanthangal, Iyyappanthangal 600056.",
    "village": "Iyyappanthangal",
    "lat": 13.0330749,
    "lng": 80.1405467,
    "found": true
  },
  {
    "station_no": "24",
    "building": "Kundrathur Panchayat Union Primary School, North Side Building, South Facing, Room No 3, Iyyappanthangal - 600056",
    "village": "North Side Building",
    "lat": 13.0427222,
    "lng": 80.1384195,
    "found": true
  },
  {
    "station_no": "25",
    "building": "Kundrathur Panchayat Union Primary School Ayyappanthangal - 600056",
    "village": "",
    "lat": 13.0506077,
    "lng": 80.0988127,
    "found": true
  },
  {
    "station_no": "26",
    "building": "Government Higher Secondary School Iyyappanthangal, Iyyappanthangal 600056.",
    "village": "Iyyappanthangal",
    "lat": 12.8227048,
    "lng": 79.6965056,
    "found": true
  },
  {
    "station_no": "27",
    "building": "Kundrathur Panchayat Union Primary School, North Side Building, South Facing, Room No 5, Iyyappanthangal - 600056",
    "village": "North Side Building",
    "lat": 13.0427222,
    "lng": 80.1384195,
    "found": true
  },
  {
    "station_no": "28",
    "building": "Masi Matriculation Higher Secondary School Srinivasapuram, Srinivasapuram 600122.",
    "village": "Srinivasapuram",
    "lat": 13.0347336,
    "lng": 80.13465459999999,
    "found": true
  },
  {
    "station_no": "29",
    "building": "Masi Matriculation Higher Secondary School Srinivasapuram, Srinivasapuram 600122.",
    "village": "Srinivasapuram",
    "lat": 13.0347336,
    "lng": 80.13465459999999,
    "found": true
  },
  {
    "station_no": "30",
    "building": "Masi Matriculation Higher Secondary School Srinivasapuram, Srinivasapuram 600122.",
    "village": "Srinivasapuram",
    "lat": 13.0347336,
    "lng": 80.13465459999999,
    "found": true
  },
  {
    "station_no": "31",
    "building": "Masi Matriculation Higher Secondary School Srinivasapuram, Srinivasapuram 600122.",
    "village": "Srinivasapuram",
    "lat": 13.0347336,
    "lng": 80.13465459999999,
    "found": true
  },
  {
    "station_no": "32",
    "building": "Masi Matriculation Higher Secondary School Srinivasapuram, Srinivasapuram 600122.",
    "village": "Srinivasapuram",
    "lat": 13.0347336,
    "lng": 80.13465459999999,
    "found": true
  },
  {
    "station_no": "33",
    "building": "Masi Matriculation Higher Secondary School Srinivasapuram, Srinivasapuram 600122.",
    "village": "Srinivasapuram",
    "lat": 13.0347336,
    "lng": 80.13465459999999,
    "found": true
  },
  {
    "station_no": "34",
    "building": "Masi Matriculation Higher Secondary School Srinivasapuram, Srinivasapuram 600122.",
    "village": "Srinivasapuram",
    "lat": 13.0347336,
    "lng": 80.13465459999999,
    "found": true
  },
  {
    "station_no": "35",
    "building": "Masi Matriculation Higher Secondary School Srinivasapuram, Srinivasapuram 600122.",
    "village": "Srinivasapuram",
    "lat": 13.0347336,
    "lng": 80.13465459999999,
    "found": true
  },
  {
    "station_no": "36",
    "building": "Panchayat Union Middle School, West Facing , Room No 1, Bharaniputhur - 600122",
    "village": "West Facing",
    "lat": 13.021994,
    "lng": 80.134018,
    "found": true
  },
  {
    "station_no": "37",
    "building": "Panchayat Union Middle School , West Facing Room No 2, Bharaniputhur - 600122",
    "village": "West Facing Room No",
    "lat": 13.021994,
    "lng": 80.134018,
    "found": true
  },
  {
    "station_no": "38",
    "building": "Panchayat Union Middle School , West Facing Room No 3 , Bharaniputhur - 600122",
    "village": "West Facing Room No",
    "lat": 13.021994,
    "lng": 80.134018,
    "found": true
  },
  {
    "station_no": "39",
    "building": "Panchayat Union Middle School , East Facing Room No 1 , Bharaniputhur - 600122",
    "village": "East Facing Room No",
    "lat": 13.021994,
    "lng": 80.134018,
    "found": true
  },
  {
    "station_no": "40",
    "building": "Panchayat Union Middle school, Old Building West Side 600122, Bharaniputhur - 600122",
    "village": "Old Building West Side",
    "lat": 13.0211435,
    "lng": 80.1313474,
    "found": true
  },
  {
    "station_no": "41",
    "building": "Panchayat Union Primay School, South West Corner Room No. 2, Bharaniputhur - 600122",
    "village": "South West Corner Room No",
    "lat": 13.0205301,
    "lng": 80.13223049999999,
    "found": true
  },
  {
    "station_no": "42",
    "building": "Panchayat Union Primay School, South West Corner Room No. 1, Bharaniputhur - 600122",
    "village": "South West Corner Room No",
    "lat": 13.0205301,
    "lng": 80.13223049999999,
    "found": true
  },
  {
    "station_no": "43",
    "building": "Panchayat Union Primay School, East Facing Building Room No 1 , Bharaniputhur - 600122",
    "village": "East Facing Building Room No",
    "lat": 13.021994,
    "lng": 80.134018,
    "found": true
  },
  {
    "station_no": "44",
    "building": "Panchayat Union Primay School, East Facing Room 2, Bharaniputhur - 600122",
    "village": "East Facing Room",
    "lat": 13.0205301,
    "lng": 80.13223049999999,
    "found": true
  },
  {
    "station_no": "45",
    "building": "Somasundara Chettiyar Government Higher Secondary School Kovur, Kovur 600122.",
    "village": "Kovur",
    "lat": 13.0316303,
    "lng": 80.1119382,
    "found": true
  },
  {
    "station_no": "46",
    "building": "Somasundara Chettiyar Government Higher Secondary School Kovur, Kovur 600122.",
    "village": "Kovur",
    "lat": 13.0316303,
    "lng": 80.1119382,
    "found": true
  },
  {
    "station_no": "47",
    "building": "Somasundara Chettiyar Government Higher Secondary School Kovur, Kovur 600122.",
    "village": "Kovur",
    "lat": 13.0316303,
    "lng": 80.1119382,
    "found": true
  },
  {
    "station_no": "48",
    "building": "Somasundara Chettiyar Government Higher Secondary School Kovur, Kovur 600122.",
    "village": "Kovur",
    "lat": 13.0316303,
    "lng": 80.1119382,
    "found": true
  },
  {
    "station_no": "49",
    "building": "Somasundara Chettiyar Government Higher Secondary School Kovur, Kovur 600122.",
    "village": "Kovur",
    "lat": 13.0316303,
    "lng": 80.1119382,
    "found": true
  },
  {
    "station_no": "50",
    "building": "Somasundara Chettiyar Government Higher Secondary School Kovur, Kovur 600122.",
    "village": "Kovur",
    "lat": 13.0316303,
    "lng": 80.1119382,
    "found": true
  },
  {
    "station_no": "51",
    "building": "Somasundaram chettiyar Government Higher Secondary School, North Facing, Room No 7, Kovur - 600128",
    "village": "North Facing",
    "lat": 13.0177744,
    "lng": 80.1114535,
    "found": true
  },
  {
    "station_no": "52",
    "building": "Somasundaram chettiyar Government Higher Secondary School, North Facing, Sec 12th STD A1,A2, Kovur - 600128",
    "village": "North Facing",
    "lat": 13.0108473,
    "lng": 80.1177335,
    "found": true
  },
  {
    "station_no": "53",
    "building": "Somasundaram chettiyar Government Higher Secondary School, North Facing Sec 12th STD B1,B2, Kovur - 600128",
    "village": "North Facing Sec",
    "lat": 13.0108473,
    "lng": 80.1177335,
    "found": true
  },
  {
    "station_no": "54",
    "building": "Somasundaram chettiyar Government Higher Secondary School, New Building, North Facing Sec 12th STD B1,B2 , Kovur - 600128",
    "village": "New Building",
    "lat": 13.0108473,
    "lng": 80.1177335,
    "found": true
  },
  {
    "station_no": "55",
    "building": "Somasundaram chettiyar Government Higher Secondary School, North Facing Sec 11th STD A Sec , Kovur - 600128",
    "village": "North Facing Sec",
    "lat": 13.0108473,
    "lng": 80.1177335,
    "found": true
  },
  {
    "station_no": "56",
    "building": "Government Adidiravidar Welfare Higher Secondary School, Moulivakka600125",
    "village": "Moulivakka",
    "lat": 13.0546418,
    "lng": 80.1927841,
    "found": true
  },
  {
    "station_no": "57",
    "building": "Government Adidiravidar Welfare Higher Secondary School, Moulivakka600125",
    "village": "Moulivakka",
    "lat": 13.0546418,
    "lng": 80.1927841,
    "found": true
  },
  {
    "station_no": "58",
    "building": "Government Adidiravidar Welfare Higher Secondary School, Moulivakka600125",
    "village": "Moulivakka",
    "lat": 13.0546418,
    "lng": 80.1927841,
    "found": true
  },
  {
    "station_no": "59",
    "building": "Government Adidiravidar Welfare Higher Secondary School, Moulivakka600125",
    "village": "Moulivakka",
    "lat": 13.0546418,
    "lng": 80.1927841,
    "found": true
  },
  {
    "station_no": "60",
    "building": "Government Adidiravidar Welfare Higher Secondary School, Moulivakka600125",
    "village": "Moulivakka",
    "lat": 13.0546418,
    "lng": 80.1927841,
    "found": true
  },
  {
    "station_no": "61",
    "building": "Little Flower Matriculation Higher Secondary School Moulivakkam, Moulivakkam-600125",
    "village": "Moulivakkam",
    "lat": 13.0324326,
    "lng": 80.2169447,
    "found": true
  },
  {
    "station_no": "62",
    "building": "Little Flower Matriculation Higher Secondary School Moulivakkam, Moulivakkam-600125",
    "village": "Moulivakkam",
    "lat": 13.0324326,
    "lng": 80.2169447,
    "found": true
  },
  {
    "station_no": "63",
    "building": "Little Flower Matriculation Higher Secondary School Moulivakkam, Moulivakkam-600125",
    "village": "Moulivakkam",
    "lat": 13.0324326,
    "lng": 80.2169447,
    "found": true
  },
  {
    "station_no": "64",
    "building": "Little Flower Matriculation Higher Secondary School Moulivakkam, Moulivakkam-600125",
    "village": "Moulivakkam",
    "lat": 13.0324326,
    "lng": 80.2169447,
    "found": true
  },
  {
    "station_no": "65",
    "building": "Little Flower Matriculation Higher Secondary School Moulivakkam, Moulivakkam-600125",
    "village": "Moulivakkam",
    "lat": 13.0324326,
    "lng": 80.2169447,
    "found": true
  },
  {
    "station_no": "66",
    "building": "Little Flower Matriculation Higher Secondary School Moulivakkam, Moulivakkam-600125",
    "village": "Moulivakkam",
    "lat": 13.0324326,
    "lng": 80.2169447,
    "found": true
  },
  {
    "station_no": "67",
    "building": "Little Flower Matriculation Higher Secondary School Moulivakkam, Moulivakkam-600125",
    "village": "Moulivakkam",
    "lat": 13.0324326,
    "lng": 80.2169447,
    "found": true
  },
  {
    "station_no": "68",
    "building": "Government High School Mugalivakkam, Mugalivakkam-600125",
    "village": "Mugalivakkam",
    "lat": 13.0212213,
    "lng": 80.1669572,
    "found": true
  },
  {
    "station_no": "69",
    "building": "Government High School Mugalivakkam, Mugalivakkam-600125",
    "village": "Mugalivakkam",
    "lat": 13.0212213,
    "lng": 80.1669572,
    "found": true
  },
  {
    "station_no": "70",
    "building": "Government High School Mugalivakkam, Mugalivakkam-600125",
    "village": "Mugalivakkam",
    "lat": 13.0212213,
    "lng": 80.1669572,
    "found": true
  },
  {
    "station_no": "71",
    "building": "Government High School Mugalivakkam, Mugalivakkam-600125",
    "village": "Mugalivakkam",
    "lat": 13.0212213,
    "lng": 80.1669572,
    "found": true
  },
  {
    "station_no": "72",
    "building": "Government High School, North Facing Room 3, Mugalivakkam - 600125",
    "village": "North Facing Room",
    "lat": 13.0212213,
    "lng": 80.1669572,
    "found": true
  },
  {
    "station_no": "73",
    "building": "Government High School, North Facing Room 4, Mugalivakkam - 600125",
    "village": "North Facing Room",
    "lat": 13.0212213,
    "lng": 80.1669572,
    "found": true
  },
  {
    "station_no": "74",
    "building": "Government High School, East Facing , Mugalivakkam - 600125",
    "village": "East Facing",
    "lat": 13.0212213,
    "lng": 80.1669572,
    "found": true
  },
  {
    "station_no": "75",
    "building": "Greater Chennai Primary School Mugalivakkam, Mugalivakkam-600125",
    "village": "Mugalivakkam",
    "lat": 13.0208125,
    "lng": 80.16745829999999,
    "found": true
  },
  {
    "station_no": "76",
    "building": "Greater Chennai Primary School Mugalivakkam, Mugalivakkam-600125",
    "village": "Mugalivakkam",
    "lat": 13.0208125,
    "lng": 80.16745829999999,
    "found": true
  },
  {
    "station_no": "77",
    "building": "Greater Chennai Primary School Mugalivakkam, Mugalivakkam-600125",
    "village": "Mugalivakkam",
    "lat": 13.0208125,
    "lng": 80.16745829999999,
    "found": true
  },
  {
    "station_no": "78",
    "building": "Greater Chennai Primary School Mugalivakkam, Mugalivakkam-600125",
    "village": "Mugalivakkam",
    "lat": 13.0208125,
    "lng": 80.16745829999999,
    "found": true
  },
  {
    "station_no": "79",
    "building": "Greater Chennai Primary School Mugalivakkam, Mugalivakkam-600125",
    "village": "Mugalivakkam",
    "lat": 13.0208125,
    "lng": 80.16745829999999,
    "found": true
  },
  {
    "station_no": "80",
    "building": "ICDS Center - 116 Mugalivakkam North Facing",
    "village": "",
    "lat": 13.0201119,
    "lng": 80.16407099999999,
    "found": true
  },
  {
    "station_no": "81",
    "building": "Greater Chennai Primary School, West Facing Room 4, Mugalivakkam - 600125",
    "village": "West Facing Room",
    "lat": 13.0341314,
    "lng": 80.1596897,
    "found": true
  },
  {
    "station_no": "82",
    "building": "Greater Chennai Primary School , West Facing Room 3, Mugalivakkam - 600125",
    "village": "West Facing Room",
    "lat": 13.0204262,
    "lng": 80.1654252,
    "found": true
  },
  {
    "station_no": "83",
    "building": "Greater Chennai Middle School Madhanandhapuram, Madhananthapuram - 600125",
    "village": "Madhananthapuram",
    "lat": 13.0227454,
    "lng": 80.1556937,
    "found": true
  },
  {
    "station_no": "84",
    "building": "Greater Chennai Primary School , North Corner West Building East Facing, Madhananthapuram - 600125",
    "village": "North Corner West Building East Facing",
    "lat": 13.0228386,
    "lng": 80.1463194,
    "found": true
  },
  {
    "station_no": "85",
    "building": "M.K.M. Matriculation Higher Secondary School Mugalivakkam, Mugalivakkam- 600125",
    "village": "Mugalivakkam",
    "lat": 13.0231453,
    "lng": 80.1628716,
    "found": true
  },
  {
    "station_no": "86",
    "building": "M.K.M. Matriculation Higher Secondary School Mugalivakkam, Mugalivakkam- 600125",
    "village": "Mugalivakkam",
    "lat": 13.0231453,
    "lng": 80.1628716,
    "found": true
  },
  {
    "station_no": "87",
    "building": "Greater Chennai Middle School Madhanandhapuram, Madhananthapuram - 600125",
    "village": "Madhananthapuram",
    "lat": 13.0227454,
    "lng": 80.1556937,
    "found": true
  },
  {
    "station_no": "88",
    "building": "M.K.M. Matriculation Higher Secondary School Mugalivakkam, Mugalivakkam- 600125",
    "village": "Mugalivakkam",
    "lat": 13.0231453,
    "lng": 80.1628716,
    "found": true
  },
  {
    "station_no": "89",
    "building": "M.K.M. Matriculation Higher Secondary School Mugalivakkam, Mugalivakkam- 600125",
    "village": "Mugalivakkam",
    "lat": 13.0231453,
    "lng": 80.1628716,
    "found": true
  },
  {
    "station_no": "90",
    "building": "Greater Chennai Primary School , East Facing Room no 1, Mugalivakkam - 600125",
    "village": "East Facing Room no",
    "lat": 13.0201248,
    "lng": 80.1656868,
    "found": true
  },
  {
    "station_no": "91",
    "building": "M.K.M. Matriculation Higher Secondary School , New Building 600116, Mugalivakkam - 600125",
    "village": "New Building",
    "lat": 13.0231453,
    "lng": 80.1628716,
    "found": true
  },
  {
    "station_no": "92",
    "building": "Greater Chennai Middle School, North Facing Room No 1, Madhananthapuram - 600125",
    "village": "North Facing Room No",
    "lat": 13.0204228,
    "lng": 80.1422805,
    "found": true
  },
  {
    "station_no": "93",
    "building": "Integrated Child Development Scheme Center :15, East Facing West Side Building, Madhanandhapuram - 600125",
    "village": "East Facing West Side Building",
    "lat": 13.0228386,
    "lng": 80.1463194,
    "found": true
  },
  {
    "station_no": "94",
    "building": "Greater Chennai Middle School Madhanandhapuram, Madhananthapuram - 600125",
    "village": "Madhananthapuram",
    "lat": 13.0227454,
    "lng": 80.1556937,
    "found": true
  },
  {
    "station_no": "95",
    "building": "ICDS Center - 516, Madhanandapuam Main Road Mugalivakkam Chennai-600125",
    "village": "Madhanandapuam Main Road Mugalivakkam Chennai",
    "lat": 13.0188093,
    "lng": 80.1604119,
    "found": true
  },
  {
    "station_no": "96",
    "building": "Greater Chennai Middle School Madhanandhapuram, Madhananthapuram - 600125",
    "village": "Madhananthapuram",
    "lat": 13.0227454,
    "lng": 80.1556937,
    "found": true
  },
  {
    "station_no": "97",
    "building": "M K M Metriculations Higher Secondary School, Nort Facing Mugalivakkam. Chennai-600125",
    "village": "Nort Facing Mugalivakkam",
    "lat": 13.0231453,
    "lng": 80.1628716,
    "found": true
  },
  {
    "station_no": "98",
    "building": "M K M Metriculations Higher Secondary School, Nort Facing Mugalivakkam. Chennai-600125",
    "village": "Nort Facing Mugalivakkam",
    "lat": 13.0231453,
    "lng": 80.1628716,
    "found": true
  },
  {
    "station_no": "99",
    "building": "Greater Chennai Middle School, East Facing, Room No 3 , Madhananthapuram - 600125",
    "village": "East Facing",
    "lat": 13.0204228,
    "lng": 80.1422805,
    "found": true
  },
  {
    "station_no": "100",
    "building": "Unit Office, Unit-35, Division - 158, Zone - 12 Nandambakkam, Nandambakkam - 600089",
    "village": "Unit",
    "lat": 13.0157879,
    "lng": 80.19292039999999,
    "found": true
  },
  {
    "station_no": "101",
    "building": "Unit Office, Unit-35, Division - 158, Zone - 12 Nandambakkam, Nandambakkam - 600089",
    "village": "Unit",
    "lat": 13.0157879,
    "lng": 80.19292039999999,
    "found": true
  },
  {
    "station_no": "102",
    "building": "Greater Chennai Primary School, East Facing West Side Building, Nandambakkam - 600069",
    "village": "East Facing West Side Building",
    "lat": 13.0341314,
    "lng": 80.1596897,
    "found": true
  },
  {
    "station_no": "103",
    "building": "Integrated Child Development Scheme Center-104, West Facing East Building , Nandambakkam - 600069",
    "village": "West Facing East Building",
    "lat": 12.9965005,
    "lng": 80.20470639999999,
    "found": true
  },
  {
    "station_no": "104",
    "building": "Tamil Nadu Establishment Co-op House Building Society , East Building, West Facing , Nandambakkam - 600069",
    "village": "East Building",
    "lat": 12.9823761,
    "lng": 80.06026450000002,
    "found": true
  },
  {
    "station_no": "105",
    "building": "Branch Library Raman Koil Street Nandambakkam, Nandambakkam - 600089",
    "village": "Nandambakkam",
    "lat": 13.0164119,
    "lng": 80.1913065,
    "found": true
  },
  {
    "station_no": "106",
    "building": "Vels Global Higher Secondary School, 137/1, Lotus Villa Vasantham Nagar, Room no 6 East Facing, Nandambakkam, Chennai - 600089.",
    "village": "Lotus Villa Vasantham Nagar",
    "lat": 13.0164295,
    "lng": 80.1899202,
    "found": true
  },
  {
    "station_no": "107",
    "building": "Vels Global Higher Secondary School, 137/1, Lotus Villa, Vasantham Nagar, Room no 7 East Facing, Nandambakkam, Chennai - 600089.",
    "village": "Lotus Villa",
    "lat": 13.1505948,
    "lng": 80.2021634,
    "found": true
  },
  {
    "station_no": "108",
    "building": "Vels Global Higher Secondary School, 137/1, Lotus Villa, Vasantham Nagar, Room no 8 East Facing, Nandambakkam, Chennai - 600089.",
    "village": "Lotus Villa",
    "lat": 13.1505948,
    "lng": 80.2021634,
    "found": true
  },
  {
    "station_no": "109",
    "building": "Vels Global Higher Secondary School, 137/1, Lotus Villa, Vasantham Nagar, Room no 9 West Facing, Nandambakkam, Chennai - 600089.",
    "village": "Lotus Villa",
    "lat": 13.1505948,
    "lng": 80.2021634,
    "found": true
  },
  {
    "station_no": "110",
    "building": "Tamil Nadu Establishment Co-op House Building Society, West Facing , Nandambakkam - 600069",
    "village": "West Facing",
    "lat": 12.9823761,
    "lng": 80.06026450000002,
    "found": true
  },
  {
    "station_no": "111",
    "building": "O/O A.E. Metro Water Office, West Facing, Manappakkam - 600125",
    "village": "West Facing",
    "lat": 12.9740439,
    "lng": 80.1814925,
    "found": true
  },
  {
    "station_no": "112",
    "building": "Greater Chennai Corporation Middle School Manapakkam,Division 157 Chennai 600125",
    "village": "Division",
    "lat": 13.011327,
    "lng": 80.16238899999999,
    "found": true
  },
  {
    "station_no": "113",
    "building": "Immanuvel Nursery & Praimary School, South Facing, Manapakkam, Chennai 600125",
    "village": "South Facing",
    "lat": 13.0548545,
    "lng": 80.2485765,
    "found": true
  },
  {
    "station_no": "114",
    "building": "Greater Chennai Corporation Middle School Manapakkam,Division 157 Chennai 600125",
    "village": "Division",
    "lat": 13.011327,
    "lng": 80.16238899999999,
    "found": true
  },
  {
    "station_no": "115",
    "building": "Greater Chennai Corporation Middle School Manapakkam,Division 157 Chennai 600125",
    "village": "Division",
    "lat": 13.011327,
    "lng": 80.16238899999999,
    "found": true
  },
  {
    "station_no": "116",
    "building": "O/O A.E. Metro Water Office, Manapakkam - 600125, West Facing",
    "village": "Manapakkam",
    "lat": 12.9740439,
    "lng": 80.1814925,
    "found": true
  },
  {
    "station_no": "117",
    "building": "Greater Chennai Middle School, East Facing Room No 3, Manappakkam - 600125",
    "village": "East Facing Room No",
    "lat": 13.0134921,
    "lng": 80.16466779999999,
    "found": true
  },
  {
    "station_no": "118",
    "building": "Greater Chennai Middle School , South Facing Room No 1, Manappakkam - 600125",
    "village": "South Facing Room No",
    "lat": 13.0134921,
    "lng": 80.16466779999999,
    "found": true
  },
  {
    "station_no": "119",
    "building": "Greater Chennai Middle School, South Facing Room No 2, Manappakkam - 600125",
    "village": "South Facing Room No",
    "lat": 13.0134921,
    "lng": 80.16466779999999,
    "found": true
  },
  {
    "station_no": "120",
    "building": "ICDS Center , Manapakkam, Chennai- 600125",
    "village": "Manapakkam",
    "lat": 13.0212637,
    "lng": 80.18324580000001,
    "found": true
  },
  {
    "station_no": "121",
    "building": "Immanuvel Nursery & Praimary School, South Facing, Manapakkam, Chennai 600125",
    "village": "South Facing",
    "lat": 13.0548545,
    "lng": 80.2485765,
    "found": true
  },
  {
    "station_no": "122",
    "building": "Emmanuvel Nursary Primary School Manapakkam, Manapakkam 600125",
    "village": "Manapakkam",
    "lat": 13.0212637,
    "lng": 80.18324580000001,
    "found": true
  },
  {
    "station_no": "123",
    "building": "Emmanuvel Nursary Primary School Manapakkam, Manapakkam 600125",
    "village": "Manapakkam",
    "lat": 13.0212637,
    "lng": 80.18324580000001,
    "found": true
  },
  {
    "station_no": "124",
    "building": "Emmanuvel Nursary Primary School Manapakkam, Manapakkam 600125",
    "village": "Manapakkam",
    "lat": 13.0212637,
    "lng": 80.18324580000001,
    "found": true
  },
  {
    "station_no": "125",
    "building": "Government Higher Secondary School Kolappakkam, Kolappakkam-600128",
    "village": "Kolappakkam",
    "lat": 13.0142211,
    "lng": 80.1594391,
    "found": true
  },
  {
    "station_no": "126",
    "building": "Government Higher Secondary School Kolappakkam, Kolappakkam-600128",
    "village": "Kolappakkam",
    "lat": 13.0142211,
    "lng": 80.1594391,
    "found": true
  },
  {
    "station_no": "127",
    "building": "St.Francis International School, East Facing Kolapakkam-600128",
    "village": "East Facing Kolapakkam",
    "lat": 13.0114576,
    "lng": 80.1543842,
    "found": true
  },
  {
    "station_no": "128",
    "building": "St.Francis International School, East Facing, LKG class Room B, Kolapakkam- 600128.",
    "village": "East Facing",
    "lat": 13.0114576,
    "lng": 80.1543842,
    "found": true
  },
  {
    "station_no": "129",
    "building": "St.Francis International School, East Facing, LKG class Room A, Kolapakkam- 600128.",
    "village": "East Facing",
    "lat": 13.0114576,
    "lng": 80.1543842,
    "found": true
  },
  {
    "station_no": "130",
    "building": "Government Higher Secondary School, Kolapakkam Chennai-600128",
    "village": "Kolapakkam Chennai",
    "lat": 13.010418,
    "lng": 80.147915,
    "found": true
  },
  {
    "station_no": "131",
    "building": "Government High School, (HM Room) West Facing, Kolapakkam - 600125",
    "village": "Kolapakkam",
    "lat": 13.0212213,
    "lng": 80.1669572,
    "found": true
  },
  {
    "station_no": "132",
    "building": "Government Higher Secondary School Kolappakkam, Kolappakkam-600128",
    "village": "Kolappakkam",
    "lat": 13.0142211,
    "lng": 80.1594391,
    "found": true
  },
  {
    "station_no": "133",
    "building": "Government Higher Secondary School Kolappakkam, Kolappakkam-600128",
    "village": "Kolappakkam",
    "lat": 13.0142211,
    "lng": 80.1594391,
    "found": true
  },
  {
    "station_no": "134",
    "building": "Government Higher Secondary School Kolappakkam, Kolappakkam-600128",
    "village": "Kolappakkam",
    "lat": 13.0142211,
    "lng": 80.1594391,
    "found": true
  },
  {
    "station_no": "135",
    "building": "Government Higher Secondary School Kolappakkam, Kolappakkam-600128",
    "village": "Kolappakkam",
    "lat": 13.0142211,
    "lng": 80.1594391,
    "found": true
  },
  {
    "station_no": "136",
    "building": "Government Higher Secondary School, New Building East Facing, Room No. 2, Kolapakkam - 600125",
    "village": "New Building East Facing",
    "lat": 13.0152122,
    "lng": 80.1795691,
    "found": true
  },
  {
    "station_no": "137",
    "building": "Sri Raghavendra Vidhyalaya Nursery &Primary School, Gerugambakkam, Gerugambakkam 600122",
    "village": "Gerugambakkam",
    "lat": 13.0316303,
    "lng": 80.1119382,
    "found": true
  },
  {
    "station_no": "138",
    "building": "Kudrathur Panchayat Union Primary School, Tharapakkam-600122",
    "village": "Tharapakkam",
    "lat": 13.0019913,
    "lng": 80.1354788,
    "found": true
  },
  {
    "station_no": "139",
    "building": "Kudrathur Panchayat Union Primary School, Gerugambakkam-600122",
    "village": "Gerugambakkam",
    "lat": 13.0210902,
    "lng": 80.12670240000001,
    "found": true
  },
  {
    "station_no": "140",
    "building": "Sri Raghavendra Vidhyalaya Nursery &Primary School, Gerugambakkam, Gerugambakkam 600122",
    "village": "Gerugambakkam",
    "lat": 13.0316303,
    "lng": 80.1119382,
    "found": true
  },
  {
    "station_no": "141",
    "building": "Sri Raghavendra Vidhyalaya Nursery &Primary School, Gerugambakkam, Gerugambakkam 600122",
    "village": "Gerugambakkam",
    "lat": 13.0316303,
    "lng": 80.1119382,
    "found": true
  },
  {
    "station_no": "142",
    "building": "Government High School Gerugambakkam, Gerugambakkam 600122",
    "village": "Gerugambakkam",
    "lat": 13.0317462,
    "lng": 80.1119385,
    "found": true
  },
  {
    "station_no": "143",
    "building": "ICDS Centre 07 Gerugambakkam, Gerugambakkam 600122",
    "village": "Gerugambakkam",
    "lat": 13.009526,
    "lng": 80.139149,
    "found": true
  },
  {
    "station_no": "144",
    "building": "Government High School Gerugambakkam, Gerugambakkam 600122",
    "village": "Gerugambakkam",
    "lat": 13.0317462,
    "lng": 80.1119385,
    "found": true
  },
  {
    "station_no": "145",
    "building": "Panchayat Union Primary School, East Side New Building 1st Std Room, Gerugambakkam - 600122",
    "village": "East Side New Building",
    "lat": 13.0100445,
    "lng": 80.1391059,
    "found": true
  },
  {
    "station_no": "146",
    "building": "Sri Raghavendra Primary School, West Facing East Side New Building 1st A Std Room, Gerugambakkam - 600122",
    "village": "West Facing East Side New Building",
    "lat": 12.9965438,
    "lng": 80.2045355,
    "found": true
  },
  {
    "station_no": "147",
    "building": "Sri Raghavendra Vidhyalaya Nursery &Primary School, Gerugambakkam, Gerugambakkam 600122",
    "village": "Gerugambakkam",
    "lat": 13.0316303,
    "lng": 80.1119382,
    "found": true
  },
  {
    "station_no": "148",
    "building": "Government High School Gerugambakkam, Gerugambakkam 600122",
    "village": "Gerugambakkam",
    "lat": 13.0317462,
    "lng": 80.1119385,
    "found": true
  },
  {
    "station_no": "149",
    "building": "Government High School Gerugambakkam, Gerugambakkam 600122",
    "village": "Gerugambakkam",
    "lat": 13.0317462,
    "lng": 80.1119385,
    "found": true
  },
  {
    "station_no": "150",
    "building": "Government High School Gerugambakkam, Gerugambakkam 600122",
    "village": "Gerugambakkam",
    "lat": 13.0317462,
    "lng": 80.1119385,
    "found": true
  },
  {
    "station_no": "151",
    "building": "Panchayat Union Primary School, West Facing, North Part, Gerugambakkam - 600122",
    "village": "West Facing",
    "lat": 12.8074054,
    "lng": 79.76675589999999,
    "found": true
  },
  {
    "station_no": "152",
    "building": "Government High School , South Builing West Corner West Facing, Gerugambakkam - 600122",
    "village": "South Builing West Corner West Facing",
    "lat": 13.0317462,
    "lng": 80.1119385,
    "found": true
  },
  {
    "station_no": "153",
    "building": "Panchayat Union Primary School, West Facing, North Part, Gerugambakkam - 600122",
    "village": "West Facing",
    "lat": 12.8074054,
    "lng": 79.76675589999999,
    "found": true
  },
  {
    "station_no": "154",
    "building": "Government High School Gerugambakkam, Gerugambakkam 600122",
    "village": "Gerugambakkam",
    "lat": 13.0317462,
    "lng": 80.1119385,
    "found": true
  },
  {
    "station_no": "155",
    "building": "Panchayat Union Primary School, Middle Building, West Facing, North Part, Gerugambakkam - 600122",
    "village": "Middle Building",
    "lat": 12.9974873,
    "lng": 80.2006371,
    "found": true
  },
  {
    "station_no": "156",
    "building": "Government High School Gerugambakkam, Gerugambakkam 600122",
    "village": "Gerugambakkam",
    "lat": 13.0317462,
    "lng": 80.1119385,
    "found": true
  },
  {
    "station_no": "157",
    "building": "Government Adidravidar Welfare Primary School. North Facing, Gerugambakkam- 600122",
    "village": "Gerugambakkam",
    "lat": 13.0117814,
    "lng": 80.1332856,
    "found": true
  },
  {
    "station_no": "158",
    "building": "Government Adidravidar Welfare Primary School. North Facing, Gerugambakkam- 600122",
    "village": "Gerugambakkam",
    "lat": 13.0117814,
    "lng": 80.1332856,
    "found": true
  },
  {
    "station_no": "159",
    "building": "Panchayat Union Middle school , North Side, Room No. 1, Thandalam - 600056",
    "village": "North Side",
    "lat": 12.8205083,
    "lng": 79.7029088,
    "found": true
  },
  {
    "station_no": "160",
    "building": "Panchayat Union Middle school , North Side, Room No. 2 , Thandalam - 600056",
    "village": "North Side",
    "lat": 12.8205083,
    "lng": 79.7029088,
    "found": true
  },
  {
    "station_no": "161",
    "building": "Government Adidharvidar welfare Primary School, Thandalam, 600128",
    "village": "Thandalam",
    "lat": 13.0117814,
    "lng": 80.1332856,
    "found": true
  },
  {
    "station_no": "162",
    "building": "Government Adidharvidar welfare Primary School, Thandalam, 600128",
    "village": "Thandalam",
    "lat": 13.0117814,
    "lng": 80.1332856,
    "found": true
  },
  {
    "station_no": "163",
    "building": "Government Adidiravidar Welfare High School Thandalam, Thandalam - 600128",
    "village": "Thandalam",
    "lat": 13.007805,
    "lng": 80.1273649,
    "found": true
  },
  {
    "station_no": "164",
    "building": "Government Adidiravidar Welfare High School Thandalam, Thandalam - 600128",
    "village": "Thandalam",
    "lat": 13.007805,
    "lng": 80.1273649,
    "found": true
  },
  {
    "station_no": "165",
    "building": "Panchayat Union Middle school , East Side Room No 1, Irandamkattalai - 600056",
    "village": "East Side Room No",
    "lat": 12.9974873,
    "lng": 80.2006371,
    "found": true
  },
  {
    "station_no": "166",
    "building": "Panchayat Union Middle school, East Side Room 2 , Irandamkattalai - 600056",
    "village": "East Side Room",
    "lat": 12.8205083,
    "lng": 79.7029088,
    "found": true
  },
  {
    "station_no": "167",
    "building": "Panchayat Union Middle school, West Side Room No 1, Irandamkattalai - 600056",
    "village": "West Side Room No",
    "lat": 12.9974873,
    "lng": 80.2006371,
    "found": true
  },
  {
    "station_no": "168",
    "building": "Panchayat Union Middle school, West Side Room No 2, Irandamkattalai - 600056",
    "village": "West Side Room No",
    "lat": 12.9974873,
    "lng": 80.2006371,
    "found": true
  },
  {
    "station_no": "169",
    "building": "St Thomas Mount Panchayat union Primary School Cowl Bazzar, Cowl Bazzar - 600074",
    "village": "Cowl Bazzar",
    "lat": 12.9840069,
    "lng": 80.1287516,
    "found": true
  },
  {
    "station_no": "170",
    "building": "St Thomas Mount Panchayat union Primary School Cowl Bazzar, Cowl Bazzar - 600074",
    "village": "Cowl Bazzar",
    "lat": 12.9840069,
    "lng": 80.1287516,
    "found": true
  },
  {
    "station_no": "171",
    "building": "St Thomas Mount Panchayat union Primary School Cowl Bazzar, Cowl Bazzar - 600074",
    "village": "Cowl Bazzar",
    "lat": 12.9840069,
    "lng": 80.1287516,
    "found": true
  },
  {
    "station_no": "172",
    "building": "St Thomas Mount Panchayat union Primary School Cowl Bazzar, Cowl Bazzar - 600074",
    "village": "Cowl Bazzar",
    "lat": 12.9840069,
    "lng": 80.1287516,
    "found": true
  },
  {
    "station_no": "173",
    "building": "St. Domnic Higher Secondary School St Thomas Mount, Poonamalle High Road St Thomas Mount 600016.",
    "village": "Poonamalle High Road St Thomas Mount",
    "lat": 13.0083474,
    "lng": 80.1963138,
    "found": true
  },
  {
    "station_no": "174",
    "building": "St. Domnic Higher Secondary School St Thomas Mount, Poonamalle High Road St Thomas Mount 600016.",
    "village": "Poonamalle High Road St Thomas Mount",
    "lat": 13.0083474,
    "lng": 80.1963138,
    "found": true
  },
  {
    "station_no": "175",
    "building": "St. Domnic Higher Secondary School St Thomas Mount, Poonamalle High Road St Thomas Mount 600016.",
    "village": "Poonamalle High Road St Thomas Mount",
    "lat": 13.0083474,
    "lng": 80.1963138,
    "found": true
  },
  {
    "station_no": "176",
    "building": "R C M High School St Thomas Mount, St. Thomas Mount - 600016",
    "village": "St",
    "lat": 13.0091091,
    "lng": 80.19520279999999,
    "found": true
  },
  {
    "station_no": "177",
    "building": "R C M Primary School St Thomas Mount, St. Thomas Mount - 600016",
    "village": "St",
    "lat": 13.005056,
    "lng": 80.19330599999999,
    "found": true
  },
  {
    "station_no": "178",
    "building": "R C M High School St Thomas Mount, St. Thomas Mount - 600016",
    "village": "St",
    "lat": 13.0091091,
    "lng": 80.19520279999999,
    "found": true
  },
  {
    "station_no": "179",
    "building": "R C M High School St Thomas Mount, St. Thomas Mount - 600016",
    "village": "St",
    "lat": 13.0091091,
    "lng": 80.19520279999999,
    "found": true
  },
  {
    "station_no": "180",
    "building": "R C M High School St Thomas Mount, St. Thomas Mount - 600016",
    "village": "St",
    "lat": 13.0091091,
    "lng": 80.19520279999999,
    "found": true
  },
  {
    "station_no": "181",
    "building": "R C M High School St Thomas Mount, St. Thomas Mount - 600016",
    "village": "St",
    "lat": 13.0091091,
    "lng": 80.19520279999999,
    "found": true
  },
  {
    "station_no": "182",
    "building": "R C M High School St Thomas Mount, St. Thomas Mount - 600016",
    "village": "St",
    "lat": 13.0091091,
    "lng": 80.19520279999999,
    "found": true
  },
  {
    "station_no": "183",
    "building": "Dr.M.G.R. Cantonment High School St Thomas Mount - 600016., St. Thomas Mount - 600016",
    "village": "St",
    "lat": 13.0129123,
    "lng": 80.19535239999999,
    "found": true
  },
  {
    "station_no": "184",
    "building": "Dr.M.G.R. Cantonment High School St Thomas Mount - 600016., St. Thomas Mount - 600016",
    "village": "St",
    "lat": 13.0129123,
    "lng": 80.19535239999999,
    "found": true
  },
  {
    "station_no": "185",
    "building": "Dr.M.G.R. Cantonment High School St Thomas Mount - 600016., St. Thomas Mount - 600016",
    "village": "St",
    "lat": 13.0129123,
    "lng": 80.19535239999999,
    "found": true
  },
  {
    "station_no": "186",
    "building": "Dr.M.G.R. Cantonment High School St Thomas Mount - 600016., St. Thomas Mount - 600016",
    "village": "St",
    "lat": 13.0129123,
    "lng": 80.19535239999999,
    "found": true
  },
  {
    "station_no": "187",
    "building": "Dr.M.G.R. Cantonment High School St Thomas Mount - 600016., St. Thomas Mount - 600016",
    "village": "St",
    "lat": 13.0129123,
    "lng": 80.19535239999999,
    "found": true
  },
  {
    "station_no": "188",
    "building": "Dr.M.G.R. Cantonment High School St Thomas Mount - 600016., St. Thomas Mount - 600016",
    "village": "St",
    "lat": 13.0129123,
    "lng": 80.19535239999999,
    "found": true
  },
  {
    "station_no": "189",
    "building": "C S I St.Thomas Higher Secondary School St Thomas Mount, St. Thomas Mount - 600016",
    "village": "St",
    "lat": 13.0076901,
    "lng": 80.1983176,
    "found": true
  },
  {
    "station_no": "190",
    "building": "C S I St.Thomas Higher Secondary School St Thomas Mount, St. Thomas Mount - 600016",
    "village": "St",
    "lat": 13.0076901,
    "lng": 80.1983176,
    "found": true
  },
  {
    "station_no": "191",
    "building": "C S I St.Thomas Higher Secondary School St Thomas Mount, St. Thomas Mount - 600016",
    "village": "St",
    "lat": 13.0076901,
    "lng": 80.1983176,
    "found": true
  },
  {
    "station_no": "192",
    "building": "C S I St.Thomas Higher Secondary School St Thomas Mount, St. Thomas Mount - 600016",
    "village": "St",
    "lat": 13.0076901,
    "lng": 80.1983176,
    "found": true
  },
  {
    "station_no": "193",
    "building": "C S I St.Thomas Higher Secondary School St Thomas Mount, St. Thomas Mount - 600016",
    "village": "St",
    "lat": 13.0076901,
    "lng": 80.1983176,
    "found": true
  },
  {
    "station_no": "194",
    "building": "C S I St.Thomas Higher Secondary School St Thomas Mount, St. Thomas Mount - 600016",
    "village": "St",
    "lat": 13.0076901,
    "lng": 80.1983176,
    "found": true
  },
  {
    "station_no": "195",
    "building": "C S I St.Thomas Higher Secondary School St Thomas Mount, St. Thomas Mount - 600016",
    "village": "St",
    "lat": 13.0076901,
    "lng": 80.1983176,
    "found": true
  },
  {
    "station_no": "196",
    "building": "Kamarajar Cantonment Primary School, St.Thomas Mount, St. Thomas Mount - 600016",
    "village": "St",
    "lat": 13.0066528,
    "lng": 80.1944807,
    "found": true
  },
  {
    "station_no": "197",
    "building": "Kamarajar Cantonment Primary School, St.Thomas Mount, St. Thomas Mount - 600016",
    "village": "St",
    "lat": 13.0066528,
    "lng": 80.1944807,
    "found": true
  },
  {
    "station_no": "198",
    "building": "Kamarajar Cantonment Primary School, St.Thomas Mount, St. Thomas Mount - 600016",
    "village": "St",
    "lat": 13.0066528,
    "lng": 80.1944807,
    "found": true
  },
  {
    "station_no": "199",
    "building": "Kamarajar Cantonment Primary School, St.Thomas Mount, St. Thomas Mount - 600016",
    "village": "St",
    "lat": 13.0066528,
    "lng": 80.1944807,
    "found": true
  },
  {
    "station_no": "200",
    "building": "Kamarajar Cantonment Primary School, St.Thomas Mount, St. Thomas Mount - 600016",
    "village": "St",
    "lat": 13.0066528,
    "lng": 80.1944807,
    "found": true
  },
  {
    "station_no": "201",
    "building": "Kamarajar Cantonment Primary School, St.Thomas Mount, St. Thomas Mount - 600016",
    "village": "St",
    "lat": 13.0066528,
    "lng": 80.1944807,
    "found": true
  },
  {
    "station_no": "202",
    "building": "Kamarajar Cantonment Primary School, St.Thomas Mount, St. Thomas Mount - 600016",
    "village": "St",
    "lat": 13.0066528,
    "lng": 80.1944807,
    "found": true
  },
  {
    "station_no": "203",
    "building": "Kamarajar Cantonment Primary School, St.Thomas Mount, St. Thomas Mount - 600016",
    "village": "St",
    "lat": 13.0066528,
    "lng": 80.1944807,
    "found": true
  },
  {
    "station_no": "204",
    "building": "St. Domnic Higher Secondary School St Thomas Mount, Poonamalle High Road St Thomas Mount 600016.",
    "village": "Poonamalle High Road St Thomas Mount",
    "lat": 13.0083474,
    "lng": 80.1963138,
    "found": true
  },
  {
    "station_no": "205",
    "building": "St. Domnic Higher Secondary School St Thomas Mount, Poonamalle High Road St Thomas Mount 600016.",
    "village": "Poonamalle High Road St Thomas Mount",
    "lat": 13.0083474,
    "lng": 80.1963138,
    "found": true
  },
  {
    "station_no": "206",
    "building": "St. Domnic Higher Secondary School St Thomas Mount, Poonamalle High Road St Thomas Mount 600016.",
    "village": "Poonamalle High Road St Thomas Mount",
    "lat": 13.0083474,
    "lng": 80.1963138,
    "found": true
  },
  {
    "station_no": "207",
    "building": "Civil Aviation Middle School Meenambakkam, Meenambakkam 600027.",
    "village": "Meenambakkam",
    "lat": 12.987454,
    "lng": 80.17534909999999,
    "found": true
  },
  {
    "station_no": "208",
    "building": "Civil Aviation Middle School Meenambakkam, Meenambakkam 600027.",
    "village": "Meenambakkam",
    "lat": 12.987454,
    "lng": 80.17534909999999,
    "found": true
  },
  {
    "station_no": "209",
    "building": "Civil Aviation Middle School Meenambakkam, Meenambakkam 600027.",
    "village": "Meenambakkam",
    "lat": 12.987454,
    "lng": 80.17534909999999,
    "found": true
  },
  {
    "station_no": "210",
    "building": "Aringnar Anna Cantonment High School, Cantonment Pallavaram, Cantonment Pallavaram-600043",
    "village": "Cantonment Pallavaram",
    "lat": 12.9717343,
    "lng": 80.1503536,
    "found": true
  },
  {
    "station_no": "211",
    "building": "Aringnar Anna Cantonment High School, Cantonment Pallavaram, Cantonment Pallavaram-600043",
    "village": "Cantonment Pallavaram",
    "lat": 12.9717343,
    "lng": 80.1503536,
    "found": true
  },
  {
    "station_no": "212",
    "building": "Aringnar Anna Cantonment High School, Cantonment Pallavaram, Cantonment Pallavaram-600043",
    "village": "Cantonment Pallavaram",
    "lat": 12.9717343,
    "lng": 80.1503536,
    "found": true
  },
  {
    "station_no": "213",
    "building": "Aringnar Anna Cantonment High School, Cantonment Pallavaram, Cantonment Pallavaram-600043",
    "village": "Cantonment Pallavaram",
    "lat": 12.9717343,
    "lng": 80.1503536,
    "found": true
  },
  {
    "station_no": "214",
    "building": "Aringnar Anna Cantonment High School, Cantonment Pallavaram, Cantonment Pallavaram-600043",
    "village": "Cantonment Pallavaram",
    "lat": 12.9717343,
    "lng": 80.1503536,
    "found": true
  },
  {
    "station_no": "215",
    "building": "Aringnar Anna Cantonment High School, Cantonment Pallavaram, Cantonment Pallavaram-600043",
    "village": "Cantonment Pallavaram",
    "lat": 12.9717343,
    "lng": 80.1503536,
    "found": true
  },
  {
    "station_no": "216",
    "building": "Aringnar Anna Cantonment High School, Cantonment Pallavaram, Cantonment Pallavaram-600043",
    "village": "Cantonment Pallavaram",
    "lat": 12.9717343,
    "lng": 80.1503536,
    "found": true
  },
  {
    "station_no": "217",
    "building": "Aringnar Anna Cantonment High School, Cantonment Pallavaram, Cantonment Pallavaram-600043",
    "village": "Cantonment Pallavaram",
    "lat": 12.9717343,
    "lng": 80.1503536,
    "found": true
  },
  {
    "station_no": "218",
    "building": "Aringnar Anna Cantonment High School, Cantonment Pallavaram, Cantonment Pallavaram-600043",
    "village": "Cantonment Pallavaram",
    "lat": 12.9717343,
    "lng": 80.1503536,
    "found": true
  },
  {
    "station_no": "219",
    "building": "Dr. APJ Abdul Kalam Cantonment Primary School, Cantonment Pallavaram, Cantonment Pallavaram-600043",
    "village": "Cantonment Pallavaram",
    "lat": 12.972,
    "lng": 80.15047050000001,
    "found": true
  },
  {
    "station_no": "220",
    "building": "Dr. APJ Abdul Kalam Cantonment Primary School, Cantonment Pallavaram, Cantonment Pallavaram-600043",
    "village": "Cantonment Pallavaram",
    "lat": 12.972,
    "lng": 80.15047050000001,
    "found": true
  },
  {
    "station_no": "221",
    "building": "Dr. APJ Abdul Kalam Cantonment Primary School, Cantonment Pallavaram, Cantonment Pallavaram-600043",
    "village": "Cantonment Pallavaram",
    "lat": 12.972,
    "lng": 80.15047050000001,
    "found": true
  },
  {
    "station_no": "222",
    "building": "Dr. APJ Abdul Kalam Cantonment Primary School, Cantonment Pallavaram, Cantonment Pallavaram-600043",
    "village": "Cantonment Pallavaram",
    "lat": 12.972,
    "lng": 80.15047050000001,
    "found": true
  },
  {
    "station_no": "223",
    "building": "Dr. APJ Abdul Kalam Cantonment Primary School, Cantonment Pallavaram, Cantonment Pallavaram-600043",
    "village": "Cantonment Pallavaram",
    "lat": 12.972,
    "lng": 80.15047050000001,
    "found": true
  },
  {
    "station_no": "224",
    "building": "Dr. APJ Abdul Kalam Cantonment Primary School, Cantonment Pallavaram, Cantonment Pallavaram-600043",
    "village": "Cantonment Pallavaram",
    "lat": 12.972,
    "lng": 80.15047050000001,
    "found": true
  },
  {
    "station_no": "225",
    "building": "Hindu Religion Middle School Alandur, Muthukumarasamy Koil Street Alandur 600016.",
    "village": "Muthukumarasamy Koil Street Alandur",
    "lat": 13.0015562,
    "lng": 80.20499559999999,
    "found": true
  },
  {
    "station_no": "226",
    "building": "Hindu Religion Middle School Alandur, Muthukumarasamy Koil Street Alandur 600016.",
    "village": "Muthukumarasamy Koil Street Alandur",
    "lat": 13.0015562,
    "lng": 80.20499559999999,
    "found": true
  },
  {
    "station_no": "227",
    "building": "Gandhi Primary School Alandur, Thadikarasamy Koil Street Alandur 600016.",
    "village": "Thadikarasamy Koil Street Alandur",
    "lat": 13.0041026,
    "lng": 80.2047333,
    "found": true
  },
  {
    "station_no": "228",
    "building": "Gandhi Primary School Alandur, Thadikarasamy Koil Street Alandur 600016.",
    "village": "Thadikarasamy Koil Street Alandur",
    "lat": 13.0041026,
    "lng": 80.2047333,
    "found": true
  },
  {
    "station_no": "229",
    "building": "Greater Chennai High School, Room No. 3, Alandur - 600016",
    "village": "Room No",
    "lat": 12.9990374,
    "lng": 80.2141796,
    "found": true
  },
  {
    "station_no": "230",
    "building": "Greater Chennai Primary School, (North) Ekambara Dabedar Street, Alandur, Ekambara Dabedar Street, Alandur 600016",
    "village": "Alandur",
    "lat": 13.0046542,
    "lng": 80.20298079999999,
    "found": true
  },
  {
    "station_no": "231",
    "building": "Greater Chennai High School Jal Street, Alandur-600016",
    "village": "Alandur",
    "lat": 13.0027811,
    "lng": 80.205003,
    "found": true
  },
  {
    "station_no": "232",
    "building": "Greater Chennai Primary School, (North) Ekambara Dabedar Street, Alandur, Ekambara Dabedar Street, Alandur 600016",
    "village": "Alandur",
    "lat": 13.0046542,
    "lng": 80.20298079999999,
    "found": true
  },
  {
    "station_no": "233",
    "building": "Greater Chennai Primary School, (North) Ekambara Dabedar Street, Alandur, Ekambara Dabedar Street, Alandur 600016",
    "village": "Alandur",
    "lat": 13.0046542,
    "lng": 80.20298079999999,
    "found": true
  },
  {
    "station_no": "234",
    "building": "Greater Chennai Primary School, Room No 3 , Alandur - 600016",
    "village": "Room No",
    "lat": 13.0004119,
    "lng": 80.20285009999999,
    "found": true
  },
  {
    "station_no": "235",
    "building": "Hindu Religion Middle School Alandur, Muthukumarasamy Koil Street Alandur 600016.",
    "village": "Muthukumarasamy Koil Street Alandur",
    "lat": 13.0015562,
    "lng": 80.20499559999999,
    "found": true
  },
  {
    "station_no": "236",
    "building": "Hindu Religion Middle School Alandur, Muthukumarasamy Koil Street Alandur 600016.",
    "village": "Muthukumarasamy Koil Street Alandur",
    "lat": 13.0015562,
    "lng": 80.20499559999999,
    "found": true
  },
  {
    "station_no": "237",
    "building": "A.J.S Nithi Higher Secondary School Alandur, Ponniyamman Koil Street, Alandur - 600016",
    "village": "Ponniyamman Koil Street",
    "lat": 12.9655621,
    "lng": 80.1960629,
    "found": true
  },
  {
    "station_no": "238",
    "building": "A.J.S Nithi Higher Secondary School Alandur, Ponniyamman Koil Street, Alandur - 600016",
    "village": "Ponniyamman Koil Street",
    "lat": 12.9655621,
    "lng": 80.1960629,
    "found": true
  },
  {
    "station_no": "239",
    "building": "A.J.S Nithi Higher Secondary School Alandur, Ponniyamman Koil Street, Alandur - 600016",
    "village": "Ponniyamman Koil Street",
    "lat": 12.9655621,
    "lng": 80.1960629,
    "found": true
  },
  {
    "station_no": "240",
    "building": "A.J.S Nithi Higher Secondary School Alandur, Ponniyamman Koil Street, Alandur - 600016",
    "village": "Ponniyamman Koil Street",
    "lat": 12.9655621,
    "lng": 80.1960629,
    "found": true
  },
  {
    "station_no": "241",
    "building": "A.J.S Nithi Higher Secondary School Alandur, Ponniyamman Koil Street, Alandur - 600016",
    "village": "Ponniyamman Koil Street",
    "lat": 12.9655621,
    "lng": 80.1960629,
    "found": true
  },
  {
    "station_no": "242",
    "building": "St. Britos College, Abraham Street, South Side, Room No 1, Adambakkam - 600088",
    "village": "Abraham Street",
    "lat": 12.9956193,
    "lng": 80.2049835,
    "found": true
  },
  {
    "station_no": "243",
    "building": "St. Britos College , Abraham Street, South Side, Room No 1, Adambakkam - 600088",
    "village": "Abraham Street",
    "lat": 12.9956193,
    "lng": 80.2049835,
    "found": true
  },
  {
    "station_no": "244",
    "building": "St.Britio's College Abraham Street, Adambakkam 600088",
    "village": "Adambakkam",
    "lat": 12.996104,
    "lng": 80.2040721,
    "found": true
  },
  {
    "station_no": "245",
    "building": "St.Britio's College Abraham Street, Adambakkam 600088",
    "village": "Adambakkam",
    "lat": 12.996104,
    "lng": 80.2040721,
    "found": true
  },
  {
    "station_no": "246",
    "building": "St.Britio's College Abraham Street, Adambakkam 600088",
    "village": "Adambakkam",
    "lat": 12.996104,
    "lng": 80.2040721,
    "found": true
  },
  {
    "station_no": "247",
    "building": "St.Britio's College Abraham Street, Adambakkam 600088",
    "village": "Adambakkam",
    "lat": 12.996104,
    "lng": 80.2040721,
    "found": true
  },
  {
    "station_no": "248",
    "building": "St.Britio's College Abraham Street, Adambakkam 600088",
    "village": "Adambakkam",
    "lat": 12.996104,
    "lng": 80.2040721,
    "found": true
  },
  {
    "station_no": "249",
    "building": "St.Britio's College Abraham Street, Adambakkam 600088",
    "village": "Adambakkam",
    "lat": 12.996104,
    "lng": 80.2040721,
    "found": true
  },
  {
    "station_no": "250",
    "building": "St.Britio's College Abraham Street, Adambakkam, Adambakkam 600088",
    "village": "Adambakkam",
    "lat": 12.996104,
    "lng": 80.2040721,
    "found": true
  },
  {
    "station_no": "251",
    "building": "St.Britio's College Abraham Street, Adambakkam, Adambakkam 600088",
    "village": "Adambakkam",
    "lat": 12.996104,
    "lng": 80.2040721,
    "found": true
  },
  {
    "station_no": "252",
    "building": "St.Britio's College Abraham Street, Adambakkam, Adambakkam 600088",
    "village": "Adambakkam",
    "lat": 12.996104,
    "lng": 80.2040721,
    "found": true
  },
  {
    "station_no": "253",
    "building": "St.Britio's College Abraham Street, Adambakkam, Adambakkam 600088",
    "village": "Adambakkam",
    "lat": 12.996104,
    "lng": 80.2040721,
    "found": true
  },
  {
    "station_no": "254",
    "building": "Greater Chennai Middle School , Adambakkam, Karuneekar Street Adambakkam - 600088",
    "village": "Adambakkam",
    "lat": 12.9927848,
    "lng": 80.2013413,
    "found": true
  },
  {
    "station_no": "255",
    "building": "Greater Chennai Middle School , Adambakkam, Karuneekar Street Adambakkam - 600088",
    "village": "Adambakkam",
    "lat": 12.9927848,
    "lng": 80.2013413,
    "found": true
  },
  {
    "station_no": "256",
    "building": "Greater Chennai Middle School , Adambakkam, Karuneekar Street Adambakkam - 600088",
    "village": "Adambakkam",
    "lat": 12.9927848,
    "lng": 80.2013413,
    "found": true
  },
  {
    "station_no": "257",
    "building": "Greater Chennai Middle School , Adambakkam, Karuneekar Street Adambakkam - 600088",
    "village": "Adambakkam",
    "lat": 12.9927848,
    "lng": 80.2013413,
    "found": true
  },
  {
    "station_no": "258",
    "building": "Jai Nursery and Primary School Adambakkam, Adambakkam 600088",
    "village": "Adambakkam",
    "lat": 12.9868537,
    "lng": 80.20030009999999,
    "found": true
  },
  {
    "station_no": "259",
    "building": "New Prince Matriculation Higher Secondary School Adambakkam, New Colony,Adambakkam 600088.",
    "village": "New Colony",
    "lat": 12.9854612,
    "lng": 80.202964,
    "found": true
  },
  {
    "station_no": "260",
    "building": "New Prince Matriculation Higher Secondary School Adambakkam, New Colony,Adambakkam 600088.",
    "village": "New Colony",
    "lat": 12.9854612,
    "lng": 80.202964,
    "found": true
  },
  {
    "station_no": "261",
    "building": "New Prince Matriculation Higher Secondary School Adambakkam, New Colony,Adambakkam 600088.",
    "village": "New Colony",
    "lat": 12.9854612,
    "lng": 80.202964,
    "found": true
  },
  {
    "station_no": "262",
    "building": "New Prince Matriculation Higher Secondary School Adambakkam, New Colony,Adambakkam 600088.",
    "village": "New Colony",
    "lat": 12.9854612,
    "lng": 80.202964,
    "found": true
  },
  {
    "station_no": "263",
    "building": "New Prince Matriculation Higher Secondary School Adambakkam, New Colony,Adambakkam 600088.",
    "village": "New Colony",
    "lat": 12.9854612,
    "lng": 80.202964,
    "found": true
  },
  {
    "station_no": "264",
    "building": "New Prince Matriculation Higher Secondary School Adambakkam, New Colony,Adambakkam 600088.",
    "village": "New Colony",
    "lat": 12.9854612,
    "lng": 80.202964,
    "found": true
  },
  {
    "station_no": "265",
    "building": "New Prince Matriculation Higher Secondary School Adambakkam, New Colony,Adambakkam 600088.",
    "village": "New Colony",
    "lat": 12.9854612,
    "lng": 80.202964,
    "found": true
  },
  {
    "station_no": "266",
    "building": "New Prince Matriculation Higher Secondary School Adambakkam, New Colony,Adambakkam 600088.",
    "village": "New Colony",
    "lat": 12.9854612,
    "lng": 80.202964,
    "found": true
  },
  {
    "station_no": "267",
    "building": "Indira Gandhi Matriculation School Adambakkam, Kundrakudi Nagar Adambakkam 600088.",
    "village": "Kundrakudi Nagar Adambakkam",
    "lat": 12.984931,
    "lng": 80.2021492,
    "found": true
  },
  {
    "station_no": "268",
    "building": "Indira Gandhi Matriculation School Adambakkam, Kundrakudi Nagar Adambakkam 600088.",
    "village": "Kundrakudi Nagar Adambakkam",
    "lat": 12.984931,
    "lng": 80.2021492,
    "found": true
  },
  {
    "station_no": "269",
    "building": "Indira Gandhi Matriculation School Adambakkam, Kundrakudi Nagar Adambakkam 600088.",
    "village": "Kundrakudi Nagar Adambakkam",
    "lat": 12.984931,
    "lng": 80.2021492,
    "found": true
  },
  {
    "station_no": "270",
    "building": "Indira Gandhi Matriculation School Adambakkam, Kundrakudi Nagar Adambakkam 600088.",
    "village": "Kundrakudi Nagar Adambakkam",
    "lat": 12.984931,
    "lng": 80.2021492,
    "found": true
  },
  {
    "station_no": "271",
    "building": "Indira Gandhi Matriculation School Adambakkam, Kundrakudi Nagar Adambakkam 600088.",
    "village": "Kundrakudi Nagar Adambakkam",
    "lat": 12.984931,
    "lng": 80.2021492,
    "found": true
  },
  {
    "station_no": "272",
    "building": "A.J.S. Nithi Higher Secondary School Alandur, Ponniyamman Koil Street, Alandur - 600016",
    "village": "Ponniyamman Koil Street",
    "lat": 12.9655621,
    "lng": 80.1960629,
    "found": true
  },
  {
    "station_no": "273",
    "building": "A.J.S. Nithi Higher Secondary School Alandur, Ponniyamman Koil Street, Alandur - 600016",
    "village": "Ponniyamman Koil Street",
    "lat": 12.9655621,
    "lng": 80.1960629,
    "found": true
  },
  {
    "station_no": "274",
    "building": "A.J.S. Nithi Higher Secondary School Alandur, Ponniyamman Koil Street, Alandur - 600016",
    "village": "Ponniyamman Koil Street",
    "lat": 12.9655621,
    "lng": 80.1960629,
    "found": true
  },
  {
    "station_no": "275",
    "building": "A.J.S. Nithi Higher Secondary School Alandur, Ponniyamman Koil Street, Alandur - 600016",
    "village": "Ponniyamman Koil Street",
    "lat": 12.9655621,
    "lng": 80.1960629,
    "found": true
  },
  {
    "station_no": "276",
    "building": "A.J.S. Nithi Higher Secondary School Alandur, Ponniyamman Koil Street, Alandur - 600016",
    "village": "Ponniyamman Koil Street",
    "lat": 12.9655621,
    "lng": 80.1960629,
    "found": true
  },
  {
    "station_no": "277",
    "building": "A.J.S. Nithi Higher Secondary School Alandur, Ponniyamman Koil Street, Alandur - 600016",
    "village": "Ponniyamman Koil Street",
    "lat": 12.9655621,
    "lng": 80.1960629,
    "found": true
  },
  {
    "station_no": "278",
    "building": "Greater Chennai High School, South Part, Alandur - 600016",
    "village": "South Part",
    "lat": 12.9990374,
    "lng": 80.2141796,
    "found": true
  },
  {
    "station_no": "279",
    "building": "Greater Chennai Primary School ,Alandur, A.R. Lane Alandur - 600016",
    "village": "Alandur",
    "lat": 12.9974873,
    "lng": 80.2006371,
    "found": true
  },
  {
    "station_no": "280",
    "building": "Greater Chennai Primary School ,Alandur, A.R. Lane Alandur - 600016",
    "village": "Alandur",
    "lat": 12.9974873,
    "lng": 80.2006371,
    "found": true
  },
  {
    "station_no": "281",
    "building": "Greater Chennai Primary School ,Alandur, A.R. Lane Alandur South Side 600016.",
    "village": "Alandur",
    "lat": 12.9974873,
    "lng": 80.2006371,
    "found": true
  },
  {
    "station_no": "282",
    "building": "Greater Chennai Primary School ,Alandur, A.R. Lane Alandur South Side 600016.",
    "village": "Alandur",
    "lat": 12.9974873,
    "lng": 80.2006371,
    "found": true
  },
  {
    "station_no": "283",
    "building": "Indira Gandhi Matriculation School , North Building Fire Statge, Adambakkam - 600088",
    "village": "North Building Fire Statge",
    "lat": 12.9956432,
    "lng": 80.2019629,
    "found": true
  },
  {
    "station_no": "284",
    "building": "Indira Gandhi Matriculation School , South Side Building East Corner Staff Room, Adambakkam - 600088",
    "village": "South Side Building East Corner Staff Room",
    "lat": 12.9956375,
    "lng": 80.2018901,
    "found": true
  },
  {
    "station_no": "285",
    "building": "St. Peters Higher Secondary School Alandur, GST Road, Alandur, 600016.",
    "village": "GST Road",
    "lat": 12.998951,
    "lng": 80.193,
    "found": true
  },
  {
    "station_no": "286",
    "building": "St. Peters Higher Secondary School Alandur, GST Road, Alandur, 600016.",
    "village": "GST Road",
    "lat": 12.998951,
    "lng": 80.193,
    "found": true
  },
  {
    "station_no": "287",
    "building": "St. Peters Higher Secondary School Alandur, GST Road, Alandur, 600016.",
    "village": "GST Road",
    "lat": 12.998951,
    "lng": 80.193,
    "found": true
  },
  {
    "station_no": "288",
    "building": "St. Peters Higher Secondary School Alandur, GST Road, Alandur, 600016.",
    "village": "GST Road",
    "lat": 12.998951,
    "lng": 80.193,
    "found": true
  },
  {
    "station_no": "289",
    "building": "C.S.I Primary School Alandur, Nobal Street, Alandur 600016.",
    "village": "Nobal Street",
    "lat": 12.9957418,
    "lng": 80.1895918,
    "found": true
  },
  {
    "station_no": "290",
    "building": "C.S.I Primary School Alandur, Nobal Street, Alandur 600016.",
    "village": "Nobal Street",
    "lat": 12.9957418,
    "lng": 80.1895918,
    "found": true
  },
  {
    "station_no": "291",
    "building": "C.S.I Primary School Alandur, Nobal Street, Alandur 600016.",
    "village": "Nobal Street",
    "lat": 12.9957418,
    "lng": 80.1895918,
    "found": true
  },
  {
    "station_no": "292",
    "building": "C.S.I Primary School Alandur, Nobal Street, Alandur 600016.",
    "village": "Nobal Street",
    "lat": 12.9957418,
    "lng": 80.1895918,
    "found": true
  },
  {
    "station_no": "293",
    "building": "Nehru Govt Boys Higher Secondary School Pazhavanthangal, College road, Pazhavanthangal- 600144",
    "village": "College road",
    "lat": 12.9864286,
    "lng": 80.1847641,
    "found": true
  },
  {
    "station_no": "294",
    "building": "Nehru Govt Boys Higher Secondary School Pazhavanthangal, College road, Pazhavanthangal- 600144",
    "village": "College road",
    "lat": 12.9864286,
    "lng": 80.1847641,
    "found": true
  },
  {
    "station_no": "295",
    "building": "Nehru Govt Boys Higher Secondary School Pazhavanthangal, College road, Pazhavanthangal- 600144",
    "village": "College road",
    "lat": 12.9864286,
    "lng": 80.1847641,
    "found": true
  },
  {
    "station_no": "296",
    "building": "Nehru Govt Boys Higher Secondary School Pazhavanthangal, College road, Pazhavanthangal- 600144",
    "village": "College road",
    "lat": 12.9864286,
    "lng": 80.1847641,
    "found": true
  },
  {
    "station_no": "297",
    "building": "Greater Chennai Primary School, South Building, North Facing, Room No. 1, Ram Nagar 8th Street, Nanganallur -600061",
    "village": "South Building",
    "lat": 12.984187,
    "lng": 80.193558,
    "found": true
  },
  {
    "station_no": "298",
    "building": "Greater Chennai Primary School, South Building, North Facing, Room No. 2, Ram Nagar 8th Street, Nanganallur -600061",
    "village": "South Building",
    "lat": 12.984187,
    "lng": 80.193558,
    "found": true
  },
  {
    "station_no": "299",
    "building": "ICDS Center: 36, Ram Nagar,Nanganallur - 600061",
    "village": "Ram Nagar",
    "lat": 12.979225,
    "lng": 80.193685,
    "found": true
  },
  {
    "station_no": "300",
    "building": "Greater Chennai Primary School, South Building, North Facing, Staff Room, Ram Nagar 8th Street, Nanganallur -600061",
    "village": "South Building",
    "lat": 12.9913596,
    "lng": 80.2117945,
    "found": true
  },
  {
    "station_no": "301",
    "building": "ICDS Center: 37, Ram Nagar , Nanganallur - 600061",
    "village": "Ram Nagar",
    "lat": 12.9819334,
    "lng": 80.1930102,
    "found": true
  },
  {
    "station_no": "302",
    "building": "Greater Chennai Primary School, Ram Nagar, Nanganallur, 600061",
    "village": "Ram Nagar",
    "lat": 12.9838844,
    "lng": 80.1944807,
    "found": true
  },
  {
    "station_no": "303",
    "building": "Greater Chennai Primary School, East Single Room,West Facing Additional Room, Ram Nagar 8th Street, Nanganallur - 600061",
    "village": "East Single Room",
    "lat": 12.9838844,
    "lng": 80.1944807,
    "found": true
  },
  {
    "station_no": "304",
    "building": "Greater Chennai Primary School, Ram Nagar, Nanganallur, Ram Nagar Nanganallur - 600061",
    "village": "Ram Nagar",
    "lat": 12.9791951,
    "lng": 80.18073729999999,
    "found": true
  },
  {
    "station_no": "305",
    "building": "Nehru Govt Boys Higher Secondary School, Palavanthangal, Collage Road-600114",
    "village": "Palavanthangal",
    "lat": 12.9864286,
    "lng": 80.1847641,
    "found": true
  },
  {
    "station_no": "306",
    "building": "D.A.V Higher Secondary School Adambakkam, Thiruvalluvar Nagar Adambakkam - 600088",
    "village": "Thiruvalluvar Nagar Adambakkam",
    "lat": 12.9970896,
    "lng": 80.2094706,
    "found": true
  },
  {
    "station_no": "307",
    "building": "D.A.V Higher Secondary School Adambakkam, Thiruvalluvar Nagar Adambakkam 600088.",
    "village": "Thiruvalluvar Nagar Adambakkam",
    "lat": 12.9970896,
    "lng": 80.2094706,
    "found": true
  },
  {
    "station_no": "308",
    "building": "D.A.V Higher Secondary School Adambakkam, Thiruvalluvar Nagar Adambakkam 600088.",
    "village": "Thiruvalluvar Nagar Adambakkam",
    "lat": 12.9970896,
    "lng": 80.2094706,
    "found": true
  },
  {
    "station_no": "309",
    "building": "D.A.V Higher Secondary School Adambakkam, Thiruvalluvar Nagar Adambakkam - 600088",
    "village": "Thiruvalluvar Nagar Adambakkam",
    "lat": 12.9970896,
    "lng": 80.2094706,
    "found": true
  },
  {
    "station_no": "310",
    "building": "D.A.V Higher Secondary School Adambakkam, Thiruvalluvar Nagar Adambakkam - 600088",
    "village": "Thiruvalluvar Nagar Adambakkam",
    "lat": 12.9970896,
    "lng": 80.2094706,
    "found": true
  },
  {
    "station_no": "311",
    "building": "D.A.V Higher Secondary School Adambakkam, Thiruvalluvar Nagar Adambakkam - 600088",
    "village": "Thiruvalluvar Nagar Adambakkam",
    "lat": 12.9970896,
    "lng": 80.2094706,
    "found": true
  },
  {
    "station_no": "312",
    "building": "Greater Chennai Primary School Vanuvampettai, Vanuvampettai 600091",
    "village": "Vanuvampettai",
    "lat": 12.9756381,
    "lng": 80.1966363,
    "found": true
  },
  {
    "station_no": "313",
    "building": "ICDS Center: 21, Pazhandiyamman Koil Street, Vanuvampet, Pazhandiyamman Koil Street, Vanuvampet- 600091",
    "village": "Pazhandiyamman Koil Street",
    "lat": 12.9593202,
    "lng": 80.1847392,
    "found": true
  },
  {
    "station_no": "314",
    "building": "Greater Chennai Primary School ,Vanuvampet, Vanuvampettai 600091",
    "village": "Vanuvampet",
    "lat": 12.9756381,
    "lng": 80.1966363,
    "found": true
  },
  {
    "station_no": "315",
    "building": "Greater Chennai Primary school , North Building West Part Room No 2, Vanuvampettai - 600091",
    "village": "North Building West Part Room No",
    "lat": 12.9726883,
    "lng": 80.19434269999999,
    "found": true
  },
  {
    "station_no": "316",
    "building": "Rajkumar Sulochana Matriculation School, 44th Street, Nanganallur Chennai-600061",
    "village": "Nanganallur Chennai",
    "lat": 12.9819209,
    "lng": 80.1876047,
    "found": true
  },
  {
    "station_no": "317",
    "building": "Greater Chennai Primary School, East Building Room No 1 , Nanganallur - 600061",
    "village": "East Building Room No",
    "lat": 12.9791951,
    "lng": 80.18073729999999,
    "found": true
  },
  {
    "station_no": "318",
    "building": "Greater Chennai Primary School , East Building Room No 2, Nanganallur - 600061",
    "village": "East Building Room No",
    "lat": 12.9791951,
    "lng": 80.18073729999999,
    "found": true
  },
  {
    "station_no": "319",
    "building": "D.A.V Higher Secondary School , South Facing, Adambakkam - 600088",
    "village": "South Facing",
    "lat": 12.9816704,
    "lng": 80.20289749999999,
    "found": true
  },
  {
    "station_no": "320",
    "building": "D.A.V Higher Secondary School , Swami Vivekananthar Block Room No.179, Adambakkam - 600088",
    "village": "Swami Vivekananthar Block Room No",
    "lat": 12.9816704,
    "lng": 80.20289749999999,
    "found": true
  },
  {
    "station_no": "321",
    "building": "D.A.V Higher Secondary School , South Facing , Adambakkam - 600088",
    "village": "South Facing",
    "lat": 12.9816704,
    "lng": 80.20289749999999,
    "found": true
  },
  {
    "station_no": "322",
    "building": "CSI Primary School, East Part , Pazhavanthagal - 600114",
    "village": "East Part",
    "lat": 12.9974873,
    "lng": 80.2006371,
    "found": true
  },
  {
    "station_no": "323",
    "building": "Greater Chennai Primary School, North Side Building Middle Room 3rd Std, Pazhavanthangal - 600114",
    "village": "North Side Building Middle Room",
    "lat": 12.9913596,
    "lng": 80.2117945,
    "found": true
  },
  {
    "station_no": "324",
    "building": "CSI Primary School, East Part, Pazhavanthangal - 600114",
    "village": "East Part",
    "lat": 12.9974873,
    "lng": 80.2006371,
    "found": true
  },
  {
    "station_no": "325",
    "building": "Nehru Government Boys Higher Secondary School, South Facing, Smart Class Room No. 1, College Road, Pazhavanthangal - 600114",
    "village": "South Facing",
    "lat": 12.9860805,
    "lng": 80.1853895,
    "found": true
  },
  {
    "station_no": "326",
    "building": "P.M.S Matriculation Higher Secondary School, East Side Building South Corner 1st Std Room, Nanganallur - 600061",
    "village": "East Side Building South Corner",
    "lat": 12.9820735,
    "lng": 80.1878287,
    "found": true
  },
  {
    "station_no": "327",
    "building": "Nehru Government Boys Higher Secondary School, South Facing, Smart Class Room No. 2, College Road, Pazhavanthangal - 600114",
    "village": "South Facing",
    "lat": 12.9860805,
    "lng": 80.1853895,
    "found": true
  },
  {
    "station_no": "328",
    "building": "Nehru Government Boys Higher Secondary School, South Facing, Room No. 3, College Road, Pazhavanthangal -600114",
    "village": "South Facing",
    "lat": 12.9860805,
    "lng": 80.1853895,
    "found": true
  },
  {
    "station_no": "329",
    "building": "P.M.S Matriculation Higher Secondary School, East Side Building South Corner 2nd Std Room, Nanganallur - 600061",
    "village": "East Side Building South Corner",
    "lat": 12.9820735,
    "lng": 80.1878287,
    "found": true
  },
  {
    "station_no": "330",
    "building": "Nehru Government Boys Higher Secondary School, South Facing, Room No. 4, College Road, Pazhavanthangal -600114",
    "village": "South Facing",
    "lat": 12.9860805,
    "lng": 80.1853895,
    "found": true
  },
  {
    "station_no": "331",
    "building": "Nehru Government Boys Higher Secondary School, Main Building, Room No 1, Pazhavanthangal - 600114",
    "village": "Main Building",
    "lat": 12.9964056,
    "lng": 80.1901166,
    "found": true
  },
  {
    "station_no": "332",
    "building": "Nehru Government Boys Higher Secondary School, Main Building, Room No 2, Pazhavanthangal - 600114",
    "village": "Main Building",
    "lat": 12.9964056,
    "lng": 80.1901166,
    "found": true
  },
  {
    "station_no": "333",
    "building": "Nehru Government Boys Higher Secondary School, Room No 3, Pazhavanthangal - 600114",
    "village": "Room No",
    "lat": 12.9878339,
    "lng": 80.1878923,
    "found": true
  },
  {
    "station_no": "334",
    "building": "Nehru Government Boys Higher Secondary School , Room No 4, Pazhavanthangal - 600114",
    "village": "Room No",
    "lat": 12.9878339,
    "lng": 80.1878923,
    "found": true
  },
  {
    "station_no": "335",
    "building": "Nehru Government Boys Higher Secondary School , Room No 5, Pazhavanthangal - 600114",
    "village": "Room No",
    "lat": 12.9878339,
    "lng": 80.1878923,
    "found": true
  },
  {
    "station_no": "336",
    "building": "Jaigopal Garodioa Government Girls Higher Secondary School Pazhavanthangal, Pazhavanthangal 600114",
    "village": "Pazhavanthangal",
    "lat": 12.9889896,
    "lng": 80.1882195,
    "found": true
  },
  {
    "station_no": "337",
    "building": "Jaigopal Garodioa Government Girls Higher Secondary School Pazhavanthangal, Pazhavanthangal 600114",
    "village": "Pazhavanthangal",
    "lat": 12.9889896,
    "lng": 80.1882195,
    "found": true
  },
  {
    "station_no": "338",
    "building": "Jaigopal Garodioa Government Girls Higher Secondary School Pazhavanthangal, Pazhavanthangal 600114",
    "village": "Pazhavanthangal",
    "lat": 12.9889896,
    "lng": 80.1882195,
    "found": true
  },
  {
    "station_no": "339",
    "building": "Jaigopal Garodioa Government Girls Higher Secondary School Pazhavanthangal, Pazhavanthangal 600114",
    "village": "Pazhavanthangal",
    "lat": 12.9889896,
    "lng": 80.1882195,
    "found": true
  },
  {
    "station_no": "340",
    "building": "Jaigopal Garodioa Government Girls Higher Secondary School Pazhavanthangal, Pazhavanthangal 600114",
    "village": "Pazhavanthangal",
    "lat": 12.9889896,
    "lng": 80.1882195,
    "found": true
  },
  {
    "station_no": "341",
    "building": "Jaigopal Garodioa Government Girls Higher Secondary School Pazhavanthangal, Pazhavanthangal 600114",
    "village": "Pazhavanthangal",
    "lat": 12.9889896,
    "lng": 80.1882195,
    "found": true
  },
  {
    "station_no": "342",
    "building": "Jaigopal Garodioa Government Girls Higher Secondary School Pazhavanthangal, Pazhavanthangal 600114",
    "village": "Pazhavanthangal",
    "lat": 12.9889896,
    "lng": 80.1882195,
    "found": true
  },
  {
    "station_no": "343",
    "building": "Jaigopal Garodioa Government Girls Higher Secondary School Pazhavanthangal, Pazhavanthangal 600114",
    "village": "Pazhavanthangal",
    "lat": 12.9889896,
    "lng": 80.1882195,
    "found": true
  },
  {
    "station_no": "344",
    "building": "Jaigopal Garodioa Government Girls Higher Secondary School Pazhavanthangal, Pazhavanthangal 600114",
    "village": "Pazhavanthangal",
    "lat": 12.9889896,
    "lng": 80.1882195,
    "found": true
  },
  {
    "station_no": "345",
    "building": "Jaigopal Garodioa Government Girls Higher Secondary School Pazhavanthangal, Pazhavanthangal 600114",
    "village": "Pazhavanthangal",
    "lat": 12.9889896,
    "lng": 80.1882195,
    "found": true
  },
  {
    "station_no": "346",
    "building": "Jaigopal Garodioa Government Girls Higher Secondary School Pazhavanthangal, Pazhavanthangal 600114",
    "village": "Pazhavanthangal",
    "lat": 12.9889896,
    "lng": 80.1882195,
    "found": true
  },
  {
    "station_no": "347",
    "building": "Jaigopal Garodioa Government Girls Higher Secondary School Pazhavanthangal, Pazhavanthangal 600114",
    "village": "Pazhavanthangal",
    "lat": 12.9889896,
    "lng": 80.1882195,
    "found": true
  },
  {
    "station_no": "348",
    "building": "Chellammal Vidyalaya Senior Secondary School Nanganallur, Nanganallur 600061.",
    "village": "Nanganallur",
    "lat": 12.9785941,
    "lng": 80.183932,
    "found": true
  },
  {
    "station_no": "349",
    "building": "Chellammal Vidyalaya Senior Secondary School Nanganallur, Nanganallur 600061.",
    "village": "Nanganallur",
    "lat": 12.9785941,
    "lng": 80.183932,
    "found": true
  },
  {
    "station_no": "350",
    "building": "Chellammal Vidyalaya Senior Secondary School Nanganallur, Nanganallur 600061.",
    "village": "Nanganallur",
    "lat": 12.9785941,
    "lng": 80.183932,
    "found": true
  },
  {
    "station_no": "351",
    "building": "Chellammal Vidyalaya Senior Secondary School Nanganallur, Nanganallur 600061.",
    "village": "Nanganallur",
    "lat": 12.9785941,
    "lng": 80.183932,
    "found": true
  },
  {
    "station_no": "352",
    "building": "Chellammal Vidyalaya Senior Secondary School Nanganallur, Nanganallur 600061.",
    "village": "Nanganallur",
    "lat": 12.9785941,
    "lng": 80.183932,
    "found": true
  },
  {
    "station_no": "353",
    "building": "Chellammal Vidyalaya Senior Secondary School Nanganallur, Nanganallur 600061.",
    "village": "Nanganallur",
    "lat": 12.9785941,
    "lng": 80.183932,
    "found": true
  },
  {
    "station_no": "354",
    "building": "Chellammal Vidyalaya Senior Secondary School Nanganallur, Nanganallur 600061.",
    "village": "Nanganallur",
    "lat": 12.9785941,
    "lng": 80.183932,
    "found": true
  },
  {
    "station_no": "355",
    "building": "Chellammal Vidyalaya Senior Secondary School Nanganallur, Nanganallur 600061.",
    "village": "Nanganallur",
    "lat": 12.9785941,
    "lng": 80.183932,
    "found": true
  },
  {
    "station_no": "356",
    "building": "Chellammal Vidyalaya Senior Secondary School Nanganallur, Nanganallur 600061.",
    "village": "Nanganallur",
    "lat": 12.9785941,
    "lng": 80.183932,
    "found": true
  },
  {
    "station_no": "357",
    "building": "Chellammal Vidyalaya Senior Secondary School Nanganallur, Nanganallur 600061.",
    "village": "Nanganallur",
    "lat": 12.9785941,
    "lng": 80.183932,
    "found": true
  },
  {
    "station_no": "358",
    "building": "Chellammal Vidyalaya Senior Secondary School Nanganallur, Nanganallur 600061.",
    "village": "Nanganallur",
    "lat": 12.9785941,
    "lng": 80.183932,
    "found": true
  },
  {
    "station_no": "359",
    "building": "Sri Venkateswara Middle School Nanganallur, Hindu Colony Nanganallur 600061.",
    "village": "Hindu Colony Nanganallur",
    "lat": 12.9757826,
    "lng": 80.1831505,
    "found": true
  },
  {
    "station_no": "360",
    "building": "Sri Venkateswara Middle School Nanganallur, Hindu Colony Nanganallur 600061.",
    "village": "Hindu Colony Nanganallur",
    "lat": 12.9757826,
    "lng": 80.1831505,
    "found": true
  },
  {
    "station_no": "361",
    "building": "Goverment Aided Middile School, Nanganallur, BV Nagar,Nanganallur Chennai-600061",
    "village": "Nanganallur",
    "lat": 12.9762675,
    "lng": 80.179807,
    "found": true
  },
  {
    "station_no": "362",
    "building": "Government Aided Primary School Nanganallur, B V Nagar 3rd Street Nanganallur - 600061",
    "village": "B V Nagar",
    "lat": 12.9734193,
    "lng": 80.1894944,
    "found": true
  },
  {
    "station_no": "363",
    "building": "Government Aided Primary School Nanganallur, B V Nagar 3rd Street Nanganallur - 600061",
    "village": "B V Nagar",
    "lat": 12.9734193,
    "lng": 80.1894944,
    "found": true
  },
  {
    "station_no": "364",
    "building": "Childrens Garden Nursery & Primary School NO : 41 Venugopalapuram Palavanthangal Chennai - 600114. (Room No:1)",
    "village": "",
    "lat": 13.1684208,
    "lng": 80.2542137,
    "found": true
  },
  {
    "station_no": "365",
    "building": "Childrens Garden Nursery & Primary School NO : 41 Venugopalapuram Palavanthangal Chennai - 600114. (Room No:1)",
    "village": "",
    "lat": 13.1684208,
    "lng": 80.2542137,
    "found": true
  },
  {
    "station_no": "366",
    "building": "Sri Venkateswara Middle School Nanganallur, Hindu Colony Nanganallur 600061.",
    "village": "Hindu Colony Nanganallur",
    "lat": 12.9757826,
    "lng": 80.1831505,
    "found": true
  },
  {
    "station_no": "367",
    "building": "Sri Venkateswara Middle School Nanganallur, Hindu Colony Nanganallur 600061.",
    "village": "Hindu Colony Nanganallur",
    "lat": 12.9757826,
    "lng": 80.1831505,
    "found": true
  },
  {
    "station_no": "368",
    "building": "Greater Chennai Primary School Thalakanancherry, K K Nagar Thalakkanancherry - 600114",
    "village": "K K Nagar Thalakkanancherry",
    "lat": 12.9747324,
    "lng": 80.1813506,
    "found": true
  },
  {
    "station_no": "369",
    "building": "Greater Chennai Primary School Thalakanancherry, K K Nagar Thalakkanancherry - 600114",
    "village": "K K Nagar Thalakkanancherry",
    "lat": 12.9747324,
    "lng": 80.1813506,
    "found": true
  },
  {
    "station_no": "370",
    "building": "Greater Chennai Primary School Thalakanancherry, K K Nagar Thalakkanancherry - 600114",
    "village": "K K Nagar Thalakkanancherry",
    "lat": 12.9747324,
    "lng": 80.1813506,
    "found": true
  },
  {
    "station_no": "371",
    "building": "Greater Chennai Primary School Thalakanancherry, K K Nagar Thalakkanancherry - 600114",
    "village": "K K Nagar Thalakkanancherry",
    "lat": 12.9747324,
    "lng": 80.1813506,
    "found": true
  },
  {
    "station_no": "372",
    "building": "Greater Chennai Primary School Thalakanancherry, K K Nagar Thalakkanancherry - 600114",
    "village": "K K Nagar Thalakkanancherry",
    "lat": 12.9747324,
    "lng": 80.1813506,
    "found": true
  },
  {
    "station_no": "373",
    "building": "Greater Chennai Primary School Thalakanancherry, K K Nagar Thalakkanancherry - 600114",
    "village": "K K Nagar Thalakkanancherry",
    "lat": 12.9747324,
    "lng": 80.1813506,
    "found": true
  },
  {
    "station_no": "374",
    "building": "Modern Senior Secondary School Nanganallur, A G S Colony Nanganallur 600061",
    "village": "A G S Colony Nanganallur",
    "lat": 12.9725278,
    "lng": 80.1857629,
    "found": true
  },
  {
    "station_no": "375",
    "building": "Modern Senior Secondary School Nanganallur, A G S Colony Nanganallur 600061",
    "village": "A G S Colony Nanganallur",
    "lat": 12.9725278,
    "lng": 80.1857629,
    "found": true
  },
  {
    "station_no": "376",
    "building": "Modern Senior Secondary School Nanganallur, A G S Colony Nanganallur 600061",
    "village": "A G S Colony Nanganallur",
    "lat": 12.9725278,
    "lng": 80.1857629,
    "found": true
  },
  {
    "station_no": "377",
    "building": "Modern Senior Secondary School Nanganallur, A G S Colony Nanganallur 600061",
    "village": "A G S Colony Nanganallur",
    "lat": 12.9725278,
    "lng": 80.1857629,
    "found": true
  },
  {
    "station_no": "378",
    "building": "Modern Senior Secondary School Nanganallur, A G S Colony Nanganallur 600061",
    "village": "A G S Colony Nanganallur",
    "lat": 12.9725278,
    "lng": 80.1857629,
    "found": true
  },
  {
    "station_no": "379",
    "building": "Modern Senior Secondary School Nanganallur, A G S Colony Nanganallur 600061",
    "village": "A G S Colony Nanganallur",
    "lat": 12.9725278,
    "lng": 80.1857629,
    "found": true
  },
  {
    "station_no": "380",
    "building": "Modern Senior Secondary School Nanganallur, A G S Colony Nanganallur 600061",
    "village": "A G S Colony Nanganallur",
    "lat": 12.9725278,
    "lng": 80.1857629,
    "found": true
  },
  {
    "station_no": "381",
    "building": "Modern Senior Secondary School Nanganallur, A G S Colony Nanganallur 600061",
    "village": "A G S Colony Nanganallur",
    "lat": 12.9725278,
    "lng": 80.1857629,
    "found": true
  },
  {
    "station_no": "382",
    "building": "Modern Senior Secondary School, Primary Wing, Nanganallur, S B I Colony Nanganallur 600061",
    "village": "Primary Wing",
    "lat": 12.9747552,
    "lng": 80.1847619,
    "found": true
  },
  {
    "station_no": "383",
    "building": "Modern Senior Secondary School, Primary Wing, Nanganallur, S B I Colony Nanganallur 600061",
    "village": "Primary Wing",
    "lat": 12.9747552,
    "lng": 80.1847619,
    "found": true
  },
  {
    "station_no": "384",
    "building": "Brilliant Matriculation Higher Secondary School, Nanganallur, 2nd Main Road Nanganallur 600061",
    "village": "Nanganallur",
    "lat": 12.9831701,
    "lng": 80.1920722,
    "found": true
  },
  {
    "station_no": "385",
    "building": "Modern Senior Secondary School, Primary Wing, Nanganallur, S B I Colony Nanganallur 600061",
    "village": "Primary Wing",
    "lat": 12.9747552,
    "lng": 80.1847619,
    "found": true
  },
  {
    "station_no": "386",
    "building": "Brilliant Matriculation Higher Secondary School, Nanganallur, 2nd Main Road Nanganallur 600061",
    "village": "Nanganallur",
    "lat": 12.9831701,
    "lng": 80.1920722,
    "found": true
  },
  {
    "station_no": "387",
    "building": "Brilliant Matriculation Higher Secondary School, Nanganallur, 2nd Main Road Nanganallur 600061",
    "village": "Nanganallur",
    "lat": 12.9831701,
    "lng": 80.1920722,
    "found": true
  },
  {
    "station_no": "388",
    "building": "Modern Senior Secondary School, Primary Wing, Nanganallur, S B I Colony Nanganallur 600061",
    "village": "Primary Wing",
    "lat": 12.9747552,
    "lng": 80.1847619,
    "found": true
  },
  {
    "station_no": "389",
    "building": "Modern Senior Secondary School, Primary Wing, Nanganallur, S B I Colony Nanganallur 600061",
    "village": "Primary Wing",
    "lat": 12.9747552,
    "lng": 80.1847619,
    "found": true
  },
  {
    "station_no": "390",
    "building": "Government Higher Secondary School Moovarasampet, Moovarasampattu 600091",
    "village": "Moovarasampattu",
    "lat": 13.0212213,
    "lng": 80.1669572,
    "found": true
  },
  {
    "station_no": "391",
    "building": "Government Higher Secondary School Moovarasampet, Moovarasampattu 600091",
    "village": "Moovarasampattu",
    "lat": 13.0212213,
    "lng": 80.1669572,
    "found": true
  },
  {
    "station_no": "392",
    "building": "Government Higher Secondary School Moovarasampet, Moovarasampattu 600091",
    "village": "Moovarasampattu",
    "lat": 13.0212213,
    "lng": 80.1669572,
    "found": true
  },
  {
    "station_no": "393",
    "building": "Government Higher Secondary School Moovarasampet, Moovarasampattu 600091",
    "village": "Moovarasampattu",
    "lat": 13.0212213,
    "lng": 80.1669572,
    "found": true
  },
  {
    "station_no": "394",
    "building": "Government Higher Secondary School Moovarasampet, Moovarasampattu 600091",
    "village": "Moovarasampattu",
    "lat": 13.0212213,
    "lng": 80.1669572,
    "found": true
  },
  {
    "station_no": "395",
    "building": "Government Higher Secondary School Moovarasampet, Moovarasampattu 600091",
    "village": "Moovarasampattu",
    "lat": 13.0212213,
    "lng": 80.1669572,
    "found": true
  },
  {
    "station_no": "396",
    "building": "St.Thomas Mount Panchayat Union Primary School Moovarasampet, Moovarasampattu 600091",
    "village": "Moovarasampattu",
    "lat": 12.9661518,
    "lng": 80.1844225,
    "found": true
  },
  {
    "station_no": "397",
    "building": "St.Thomas Mount Panchayat Union Primary School Moovarasampet, Moovarasampattu 600091",
    "village": "Moovarasampattu",
    "lat": 12.9661518,
    "lng": 80.1844225,
    "found": true
  },
  {
    "station_no": "398",
    "building": "St.Thomas Mount Panchayat Union Primary School Moovarasampet, Moovarasampattu 600091",
    "village": "Moovarasampattu",
    "lat": 12.9661518,
    "lng": 80.1844225,
    "found": true
  },
  {
    "station_no": "399",
    "building": "St.Thomas Mount Panchayat Union Primary School Moovarasampet, Moovarasampattu 600091",
    "village": "Moovarasampattu",
    "lat": 12.9661518,
    "lng": 80.1844225,
    "found": true
  },
  {
    "station_no": "400",
    "building": "St.Thomas Mount Panchayat Union Primary School Moovarasampet, Moovarasampattu 600091",
    "village": "Moovarasampattu",
    "lat": 12.9661518,
    "lng": 80.1844225,
    "found": true
  },
  {
    "station_no": "401",
    "building": "St.Thomas Mount Panchayat Union Primary School Moovarasampet, Moovarasampattu 600091",
    "village": "Moovarasampattu",
    "lat": 12.9661518,
    "lng": 80.1844225,
    "found": true
  }
]